[{"uuid": "fcea56c0-3f78-bda0-2249-0bee1f327d78", "date": "019K13",
   "duration": 60, "sector": "maintenance", "project": null,
   "label": "Amélioration de mon Bashprofile"},
  {"uuid": "06b9c384-5335-ab90-a4ea-56fc2c63b733", "date": "019K10",
    "duration": 320, "sector": "research", "project": null,
    "label": "Expériences photographiques"},
  {"uuid": "fa9e1f44-7c17-c43b-7773-c271c98e013d", "date": "019K09",
    "duration": 320, "sector": "research", "project": null,
    "label": "Expériences photographiques"},
  {"uuid": "bf603dcc-d361-63a7-5dba-74cdf080f2cf", "date": "019K08",
    "duration": 120, "sector": "writing", "project": "planet",
    "label": "Ecriture de l'article sur le Kata du tennis appliqué à OCaml"},
  {"uuid": "eb7b1777-af15-64d3-b65d-34406af0a128", "date": "019K08",
    "duration": 200, "sector": "research", "project": null,
    "label": "Expériences photographiques"}]