[{"uuid": "fea6035c-e097-15b2-7175-01804b5645aa", "date": "020L13",
   "duration": 450, "sector": "programming", "project": "preface",
   "label": "Test dirigés par les propriétés pour les comonades"},
  {"uuid": "853207c8-c6a6-da03-f4ed-8326b5722213", "date": "020L12",
    "duration": 200, "sector": "programming", "project": null,
    "label": "Prototype d'un Webring"},
  {"uuid": "93d3f516-a063-f16a-5a0c-b2446347b8d0", "date": "020L11",
    "duration": 450, "sector": "programming", "project": null,
    "label": "Expériences avec Arrow et les suspensions"},
  {"uuid": "9fef1146-fcb7-24ad-e66d-fa907ff6e4ff", "date": "020L10",
    "duration": 300, "sector": "research", "project": null,
    "label": "Collecte de matériel pour l'article sur le café"},
  {"uuid": "d049a07c-36f8-b752-525d-e44cf860d27d", "date": "020L09",
    "duration": 120, "sector": "programming", "project": "preface",
    "label": "Expériences sur les tests dirigés par les propriétés"},
  {"uuid": "0b96bf95-27dd-850b-a90f-c082586aea76", "date": "020L08",
    "duration": 250, "sector": "programming", "project": "preface",
    "label": "Continuation d'expériences sur les tests dirigés par les propriétés"},
  {"uuid": "a1c9c841-6796-f0fa-dd5e-8dcdbdf78475", "date": "020L07",
    "duration": 350, "sector": "visual", "project": null,
    "label": "Expériences sur le design pour support de présentation"},
  {"uuid": "5382cdd4-2d39-8646-dff2-b3a4e12772c9", "date": "020L06",
    "duration": 380, "sector": "programming", "project": "preface",
    "label": "Réécriture des tests dirigés par les propriétés"},
  {"uuid": "2cf444d7-a8bf-00d8-f12f-00983e612714", "date": "020L05",
    "duration": 350, "sector": "programming", "project": "preface",
    "label": "Modifications des tests (en vue d'éraridiquer l'abus de Obj.magic)"},
  {"uuid": "a0d0fa36-9552-d256-48f2-f45d51cc4b25", "date": "020L04",
    "duration": 60, "sector": "programming", "project": "preface",
    "label": "Expériences autours des tests"},
  {"uuid": "fefff1bc-cb0c-01e4-e907-8315a80ceb53", "date": "020L03",
    "duration": 120, "sector": "programming", "project": "preface",
    "label": "Remplacement typographique (eq -> equal) et utilisation du paquet Either pour simplifier la définition de Selectives"},
  {"uuid": "a82046e1-cd9e-72ff-f931-1b3a08f47e0f", "date": "020L02",
    "duration": 120, "sector": "programming", "project": "preface",
    "label": "Expériences autour du regroupement de modules"},
  {"uuid": "5d5bae06-45f9-b2dc-e6bc-e5cfd8ac1a5a", "date": "020L01",
    "duration": 250, "sector": "writing", "project": null,
    "label": "Préparation du Talk sur les Binding pour Cuuti"},
  {"uuid": "ab96373c-5d17-cde0-9a3b-ee4719eff0b1", "date": "020K30",
    "duration": 200, "sector": "programming", "project": "orion",
    "label": "Implémentation de Brick"},
  {"uuid": "afe76d8b-8cfa-ad1e-0d76-a0df07d0c1d4", "date": "020K29",
    "duration": 500, "sector": "programming", "project": "orion",
    "label": "Amélioration de l'infrastructure de test pour tester correctemment l'IO"},
  {"uuid": "b49c2de8-fb60-9bfc-2648-e18ec4c34e00", "date": "020K28",
    "duration": 300, "sector": "programming", "project": "orion",
    "label": "Démarrage de la bibliothèque nécessaire á l'écriture des services"},
  {"uuid": "fa010b7a-ae23-b5ed-a0c3-e079c08697bd", "date": "020K27",
    "duration": 20, "sector": "programming", "project": null,
    "label": "Expériences avec Dmlenu"},
  {"uuid": "2e024898-73db-a0f5-d482-37f6a7468ed6", "date": "020K27",
    "duration": 320, "sector": "programming", "project": "orion",
    "label": "Expérimentations sur les formats de serialisation"},
  {"uuid": "1062382c-bb91-8302-66bb-6242208ee4cd", "date": "020K26",
    "duration": 25, "sector": "programming", "project": null,
    "label": "Expériences avec Dmlenu"},
  {"uuid": "bd270c18-7f98-eb2f-6066-0f73bab5e606", "date": "020K24",
    "duration": 780, "sector": "writing", "project": null,
    "label": "Etats d'âmes : conversions d'articles"},
  {"uuid": "d457d8f3-af6b-9845-0a03-ec03d57fda56", "date": "020K23",
    "duration": 400, "sector": "writing", "project": null,
    "label": "Etats d'âmes : conversions d'articles"},
  {"uuid": "c971e0df-ad03-e43f-e762-1c1e4bd635e2", "date": "020K22",
    "duration": 25, "sector": "programming", "project": "preface",
    "label": "Mise à jour des Free Applicative et Free Selective"},
  {"uuid": "b1856dab-98fb-3567-8aed-84fc359388c1", "date": "020K22",
    "duration": 200, "sector": "writing", "project": null,
    "label": "Etats d'âmes : transposition d'articles en document"},
  {"uuid": "78b53a89-d0e6-1aac-2fa6-567fcd6e25b3", "date": "020K21",
    "duration": 300, "sector": "maintenance", "project": null,
    "label": "Configuration ArchLinux"},
  {"uuid": "ab680c60-b2e1-0de9-510d-de674ed5daa6", "date": "020K21",
    "duration": 350, "sector": "programming", "project": null,
    "label": "Hacking avec Xmonad"},
  {"uuid": "842c7549-7c25-3e43-fa5f-2e9a4d3070ef", "date": "020K20",
    "duration": 450, "sector": "maintenance", "project": null,
    "label": "Configuration de ArchLinux"},
  {"uuid": "f3b2979b-59a2-51ca-a52c-e16871b915c9", "date": "020K19",
    "duration": 300, "sector": "maintenance", "project": null,
    "label": "Configuration de ArchLinux"},
  {"uuid": "74f56202-8257-4806-7453-cc10b70b96c5", "date": "020K18",
    "duration": 280, "sector": "maintenance", "project": null,
    "label": "Configuration ArchLinux"},
  {"uuid": "6387d8c1-268d-17c8-fbe9-cc6a88ee5dec", "date": "020K17",
    "duration": 300, "sector": "maintenance", "project": null,
    "label": "Installation de ArchLinux sur ma machine personnelle"},
  {"uuid": "b3d373cc-2a57-a39b-751d-37d00b7d1492", "date": "020K15",
    "duration": 400, "sector": "programming", "project": "preface",
    "label": "Implémentation des Free Selectives"},
  {"uuid": "af651656-24cc-db39-8628-08dd25ba997a", "date": "020K14",
    "duration": 360, "sector": "programming", "project": "preface",
    "label": "Amélioration de l'API des Free Applicatives et démarrage des Free Selectives"},
  {"uuid": "cc5e7d7e-29ba-3c64-1025-4398f9d1800c", "date": "020K13",
    "duration": 250, "sector": "programming", "project": "preface",
    "label": "Implémentation des Free Applicative"},
  {"uuid": "69bff59e-ef04-01c3-bd5c-63b1c02ee928", "date": "020K09",
    "duration": 100, "sector": "programming", "project": "preface",
    "label": "Introduction de Validate"},
  {"uuid": "41918e60-0d21-6a75-db54-f266d1ebfdbc", "date": "020K09",
    "duration": 180, "sector": "programming", "project": "preface",
    "label": "Amélioration des Validations"},
  {"uuid": "930ec530-5c38-c761-a50e-9f75e216d6b8", "date": "020K09",
    "duration": 480, "sector": "writing", "project": null,
    "label": "Rédaction du talk sur les effets algébriques pour la conférence Codeurs en Seine"},
  {"uuid": "fbf45770-86f9-4a5b-0993-02bdc43f0be3", "date": "020K08",
    "duration": 200, "sector": "programming", "project": "preface",
    "label": "Paramétrisation de Validation"},
  {"uuid": "30c68998-a78a-a93c-fe4c-e80b516c2e51", "date": "020K06",
    "duration": 380, "sector": "maintenance", "project": null,
    "label": "Mise en place d'un nouveau bureau"},
  {"uuid": "6933afde-e323-0f6d-6460-adff9e145b69", "date": "020K06",
    "duration": 60, "sector": "programming", "project": "preface",
    "label": "Impl. de la classe Alt"},
  {"uuid": "15ba78fb-05ef-1838-4406-b066895893d3", "date": "020K01",
    "duration": 250, "sector": "maintenance", "project": "planet",
    "label": "Saisie des données et petites mises à jour"},
  {"uuid": "33f30ed2-40cf-1f32-6677-7f5f1177625d", "date": "020K01",
    "duration": 30, "sector": "programming", "project": "preface",
    "label": "Implémentation de Result"},
  {"uuid": "8d64f204-3ade-8a7c-1716-2082148f50af", "date": "020J29",
    "duration": 350, "sector": "writing", "project": null,
    "label": "Préparation du talk Codeurs en Seine"},
  {"uuid": "8d64f204-3ade-8a7c-1716-2082148f50af", "date": "020J22",
    "duration": 350, "sector": "writing", "project": null,
    "label": "Préparation du talk Codeurs en Seine"},
  {"uuid": "8d64f204-3ade-8a7c-1716-2082148f50af", "date": "020J18",
    "duration": 350, "sector": "writing", "project": null,
    "label": "Préparation du talk Codeurs en Seine"},
  {"uuid": "8d64f204-3ade-8a7c-1716-2082148f50af", "date": "020J17",
    "duration": 350, "sector": "writing", "project": null,
    "label": "Préparation du talk Codeurs en Seine"},
  {"uuid": "b3569266-9f70-d0c8-5d55-7624549ca92b", "date": "020J13",
    "duration": 300, "sector": "writing", "project": null,
    "label": "Préparation du talk Codeurs en Seine"},
  {"uuid": "4b1e1b71-fa37-574e-6807-a5adacab9977", "date": "020J07",
    "duration": 300, "sector": "visual", "project": null,
    "label": "Rebranding des slides de Nicolas"},
  {"uuid": "28cde82b-60e6-8255-108d-4b29dced9842", "date": "020J05",
    "duration": 200, "sector": "visual", "project": null,
    "label": "Rebranding des slides de Nicolas"},
  {"uuid": "e262552e-9ca4-67e5-edcc-c7e520b307e4", "date": "020J03",
    "duration": 650, "sector": "writing", "project": null,
    "label": "Ecriture du talk sur les formlets"},
  {"uuid": "e0b6f86f-3308-2022-1fad-dc03c46cd670", "date": "020J02",
    "duration": 200, "sector": "writing", "project": null,
    "label": "Ecriture du talk sur les formlets"},
  {"uuid": "f7c519ef-0110-c568-1a4e-ae0aa1cb3bba", "date": "020I28",
    "duration": 120, "sector": "maintenance", "project": null,
    "label": "Configuration Fujifilm"},
  {"uuid": "0ad20b8f-206f-e490-3064-22b19941b98c", "date": "020I27",
    "duration": 350, "sector": "maintenance", "project": null,
    "label": "Configuration Fujifilm"},
  {"uuid": "952129e2-e301-3e9f-910c-e39c99fc1f40", "date": "020I23",
    "duration": 200, "sector": "writing", "project": null,
    "label": "Traduction des sous-titres de FPTower"},
  {"uuid": "c81eff67-60cf-bd99-56fa-eae85a420cd6", "date": "020I23",
    "duration": 30, "sector": "maintenance", "project": "planet",
    "label": "Mise à jours des données et mise à jours des paquets"},
  {"uuid": "f8b4efca-a831-31b7-a1db-63e9276af8bb", "date": "020I23",
    "duration": 300, "sector": "programming", "project": "preface",
    "label": "Implémentation des Monades plus"},
  {"uuid": "edb05e19-3de2-02c8-a185-b64db5c0d21f", "date": "020I22",
    "duration": 500, "sector": "writing", "project": null,
    "label": "Traduction de sous-titres pour FPTower"},
  {"uuid": "b54d9167-56d3-6513-3eb7-afd6c48c31ae", "date": "020I21",
    "duration": 450, "sector": "writing", "project": null,
    "label": "Traduction des sous-titres pour FPTower"},
  {"uuid": "ceaa6870-fcff-4754-9fba-ecdeaaea4f7a", "date": "020H26",
    "duration": 15, "sector": "programming", "project": "planet",
    "label": "Re-rendu de la barre de progression en sticky pour les articles"},
  {"uuid": "cb7cd8b7-803f-2ee0-5b1e-fe5cfca3fbc4", "date": "020H25",
    "duration": 30, "sector": "programming", "project": "preface",
    "label": "Ajout de test pour les Alternatives"},
  {"uuid": "aa5fb06f-4f3c-87f9-6c36-9456a8a30186", "date": "020H25",
    "duration": 200, "sector": "programming", "project": "planet",
    "label": "Réduction de la génération de données à la volée"},
  {"uuid": "246359f0-116e-2f82-1ac4-5f470b38984b", "date": "020H19",
    "duration": 300, "sector": "writing", "project": null,
    "label": "Traduction FR pour FP-tower"},
  {"uuid": "de83eb18-f136-4884-0cce-4805a619a97e", "date": "020H18",
    "duration": 200, "sector": "writing", "project": null,
    "label": "Traduction FR pour FP-tower"},
  {"uuid": "beb1c6de-8178-aa20-493b-c3dcd98ba539", "date": "020H17",
    "duration": 150, "sector": "writing", "project": null,
    "label": "Traduction FR pour FP-tower"},
  {"uuid": "9ef52d15-7907-f976-ddb3-1189f73a9e40", "date": "020H11",
    "duration": 200, "sector": "programming", "project": "preface",
    "label": "Finalisation et test des Alternatives"},
  {"uuid": "6cb47ebc-5fd1-9048-6c95-296b6c3742e4", "date": "020H11",
    "duration": 30, "sector": "programming", "project": "preface",
    "label": "Correctif sur les alternatives"},
  {"uuid": "9e10eda5-f06f-f7b1-789c-98072ebd1de5", "date": "020H11",
    "duration": 60, "sector": "programming", "project": "planet",
    "label": "Légère modification du graphique de tracking"},
  {"uuid": "8d06b64b-7d4e-735e-5765-82d75b041581", "date": "020H10",
    "duration": 60, "sector": "maintenance", "project": "planet",
    "label": "Saisie de données et modifications de status"},
  {"uuid": "3079f272-01cd-5c5f-db27-9a810ad63ca5", "date": "020H10",
    "duration": 100, "sector": "programming", "project": "preface",
    "label": "Implémentation des alternatives"},
  {"uuid": "3f631687-0b63-64a3-9f50-d1e8e1ae6e2a", "date": "020G26",
    "duration": 450, "sector": "audio", "project": null,
    "label": "Expériences avec Sunvox"},
  {"uuid": "23f2b7db-3044-0ddd-7c03-37ef53625ec0", "date": "020G25",
    "duration": 780, "sector": "audio", "project": null,
    "label": "Expériences avec Sunvox"},
  {"uuid": "337a528d-e562-0ee9-d3ea-b1e038966165", "date": "020G24",
    "duration": 450, "sector": "audio", "project": null,
    "label": "Expériences avec Sunvox"},
  {"uuid": "ce8423c2-f422-3cb0-06b3-0874f76aa4e0", "date": "020G23",
    "duration": 280, "sector": "audio", "project": null,
    "label": "Expériences avec Sunvox"},
  {"uuid": "43bca18d-1b20-c09c-da85-c2f6f3bf6fdf", "date": "020G22",
    "duration": 230, "sector": "audio", "project": null,
    "label": "Expériences avec Sunvox"},
  {"uuid": "4daa34ea-2ad5-3f42-c7bd-45bbd064fff9", "date": "020G18",
    "duration": 10, "sector": "maintenance", "project": "planet",
    "label": "Correctifs de typos"},
  {"uuid": "bddc1278-1d07-2462-5514-18672c8b00f8", "date": "020G07",
    "duration": 250, "sector": "research", "project": null,
    "label": "Lecture des papiers séminaux de la programmation avec des effets algébriques"},
  {"uuid": "90c3459c-fadd-68d9-4da1-c5289afe72df", "date": "020G06",
    "duration": 300, "sector": "research", "project": null,
    "label": "Lecture des papiers séminaux de la programmation avec des effets algébriques"},
  {"uuid": "241271eb-1f94-15af-529d-4e1f286a716a", "date": "020G05",
    "duration": 200, "sector": "research", "project": null,
    "label": "Lecture des papiers séminaux de la programmation avec des effets algébriques"},
  {"uuid": "790acc2e-ac27-9c89-ecfa-6abcbe2a4b29", "date": "020G04",
    "duration": 200, "sector": "research", "project": null,
    "label": "Lecture des papiers séminaux de la programmation avec des effets algébriques"},
  {"uuid": "809642e5-90a1-b0a0-0af6-996b4c77b5c1", "date": "020G03",
    "duration": 300, "sector": "research", "project": null,
    "label": "Lecture des papiers séminaux de la programmation avec des effets algébriques"},
  {"uuid": "44106ba2-fbe0-ac2e-fb3a-65cf00541f9d", "date": "020G02",
    "duration": 450, "sector": "research", "project": null,
    "label": "Lecture des papiers séminaux de la programmation avec des effets algébriques"},
  {"uuid": "2b2da873-a0c9-1608-8181-d0ec530c61cd", "date": "020G01",
    "duration": 200, "sector": "research", "project": null,
    "label": "Lecture des papiers séminaux de la programmation avec des effets algébriques"},
  {"uuid": "d9e92467-fbb0-512a-3710-03f8c67d3b0e", "date": "020F30",
    "duration": 200, "sector": "research", "project": null,
    "label": "Bibliographie pour la présentation sur les effets (n°3)"},
  {"uuid": "04a48ba7-3ebb-bc7d-5e00-5a72794cf868", "date": "020F29",
    "duration": 200, "sector": "programming", "project": null,
    "label": "Exposition des modules Filename.{Unix, Cygwin, Win32} pour OCaml"},
  {"uuid": "c2fdf173-cb68-b15a-a6ae-603087362207", "date": "020F28",
    "duration": 200, "sector": "research", "project": "orion",
    "label": "Collecte des fonctionnalités à implémenter"},
  {"uuid": "e0cbf61b-d387-4e05-078e-05f394006f87", "date": "020F28",
    "duration": 100, "sector": "writing", "project": null,
    "label": "Correctifs de traduction pour les sous-titres de fp-tower"},
  {"uuid": "2d6e2173-b312-ed83-cfad-467bc39e6f66", "date": "020F27",
    "duration": 320, "sector": "research", "project": "orion",
    "label": "Expériences avec Mirage, Irmin et Git"},
  {"uuid": "5fd7cf40-c1e6-7f66-f686-456ed0a83dac", "date": "020F26",
    "duration": 250, "sector": "writing", "project": null,
    "label": "Traduction d'un épisode de fp-tower"},
  {"uuid": "3efec7b6-f62b-83fb-648e-e14a65873e83", "date": "020F26",
    "duration": 300, "sector": "programming", "project": "orion",
    "label": "Expériences avec Irmin, OCaml git et MirageOS"},
  {"uuid": "510aad17-66ce-c6f1-2dcf-22915eac5f75", "date": "020F25",
    "duration": 200, "sector": "programming", "project": "orion",
    "label": "Expériences avec Irmin, OCaml git et MirageOS"},
  {"uuid": "b4a0ba03-3c61-9f26-6215-fc013f641075", "date": "020F24",
    "duration": 100, "sector": "maintenance", "project": "planet",
    "label": "Saisie de logs et mise à jour de pages"},
  {"uuid": "dc0e3e8b-6828-96b4-cf0e-f6e7d690cb6f", "date": "020F24",
    "duration": 60, "sector": "programming", "project": null,
    "label": "Ajout d'astuces en cas d'erreur d'usage de modules pour OCaml"},
  {"uuid": "b6795bd7-e658-5503-6c28-053ffffdd3b5", "date": "020F23",
    "duration": 200, "sector": "writing", "project": null,
    "label": "Réécriture du talk sur les effets"},
  {"uuid": "0d983c36-2d26-7192-7ae3-86f3f4f01c7d", "date": "020F22",
    "duration": 500, "sector": "research", "project": null,
    "label": "Expériences avec MirageOS"},
  {"uuid": "2ffc5b1b-460b-20c0-07da-c11b0af46ca8", "date": "020F21",
    "duration": 200, "sector": "research", "project": null,
    "label": "Expériences avec MirageOS"},
  {"uuid": "0e93c516-e9ab-d7b6-1245-288acfcd0014", "date": "020F20",
    "duration": 450, "sector": "reading", "project": null,
    "label": "Lecture et expériences via le livre Category Theory in context de E. Riehl"},
  {"uuid": "8c50ba08-03e3-1cbf-40dc-0daa8eb7418d", "date": "020F19",
    "duration": 200, "sector": "reading", "project": null,
    "label": "Lecture et expériences via le livre Category Theory in context de E. Riehl"},
  {"uuid": "96aedee5-a701-c53d-ea23-e1e270034786", "date": "020F18",
    "duration": 200, "sector": "research", "project": "preface",
    "label": "Définition des fonctionnalités majeures"},
  {"uuid": "0a6d5951-10d1-3f92-1bb8-b59c2aad19e1", "date": "020F17",
    "duration": 200, "sector": "writing", "project": null,
    "label": "Traduction francophone pour un épisode de FP-tower"},
  {"uuid": "d32994be-4eb0-f39d-d906-a37fe9b58c74", "date": "020F15",
    "duration": 30, "sector": "research", "project": "preface",
    "label": "Revue de la branche sur les Arrows"},
  {"uuid": "401d7701-d5a2-9c05-8c80-cd52e7ee8378", "date": "020F14",
    "duration": 100, "sector": "programming", "project": null,
    "label": "Amélioration des astuces d'aide à la compilation pour OCaml"},
  {"uuid": "d76e357a-832c-0755-1405-aedd9dd349ff", "date": "020F13",
    "duration": 120, "sector": "programming", "project": null,
    "label": "Implémentation d'astuces, aide à la compilation, dans le compilateur d'OCaml pour les modules, modules types et types de classes"},
  {"uuid": "39c567f5-cba0-9304-1fa6-41d666643c0b", "date": "020F12",
    "duration": 100, "sector": "maintenance", "project": null,
    "label": "Mise en place d'un environnement de développement pour des contributions potentielles à OCaml"},
  {"uuid": "f59d2f14-1932-5c55-7978-ed964b459fd0", "date": "020F11",
    "duration": 300, "sector": "programming", "project": "preface",
    "label": "Revue et expériences d'utilisation de la bibliothèque"},
  {"uuid": "473dc099-8ca9-df84-526c-503372e075e5", "date": "020F10",
    "duration": 210, "sector": "programming", "project": "orion",
    "label": "Expériences d'utilisation de Preface dans Orion"},
  {"uuid": "528123ae-1cc1-3c5c-98a8-d57e67ed8307", "date": "020F09",
    "duration": 200, "sector": "research", "project": "orion",
    "label": "Choix des premières fonctionnalitées à implémenter"},
  {"uuid": "87ecea0b-9f86-14ab-3475-396088ada4e3", "date": "020F08",
    "duration": 100, "sector": "programming", "project": "orion",
    "label": "Revue, et expérimentations"},
  {"uuid": "03f46d15-4c30-9927-1e9a-a3660d412b2a", "date": "020F07",
    "duration": 200, "sector": "programming", "project": "orion",
    "label": "Expériences entre Transept et Orion"},
  {"uuid": "6505d4f9-aa6b-3731-ed71-3202e95366c4", "date": "020F07",
    "duration": 200, "sector": "research", "project": "qian",
    "label": "Mise à jours de Elm en vue d'une potentielle et providentielle version 2... qui n'arrivera peut être jamais..."},
  {"uuid": "7b46f504-c215-1284-fc5b-2e200293eb45", "date": "020F06",
    "duration": 120, "sector": "programming", "project": "preface",
    "label": "Implémentation de Foldable"},
  {"uuid": "82d03cb1-c7ab-0c5c-cd5a-54d9b7563167", "date": "020F05",
    "duration": 300, "sector": "programming", "project": "preface",
    "label": "Implémentation, documentation et expérimentation autour de Foldable"},
  {"uuid": "ab7a037d-7284-6501-eaf0-9ccd7e21cefb", "date": "020F04",
    "duration": 60, "sector": "programming", "project": "preface",
    "label": "Démarrage de l'implémentation de Foldable"},
  {"uuid": "3e5ffbcb-a30d-d54b-7746-62f442a91c0c", "date": "020F03",
    "duration": 160, "sector": "programming", "project": "preface",
    "label": "Relecture de la réorganisation des tests"},
  {"uuid": "678c0c7d-5770-3f09-70b0-b2cdcbfef5da", "date": "020F02",
    "duration": 120, "sector": "programming", "project": "preface",
    "label": "Revue (Reader et Writer) et petits correctifs"},
  {"uuid": "77e142dc-64c3-7299-f060-7e5c7c58ac8a", "date": "020F02",
    "duration": 250, "sector": "research", "project": null,
    "label": "Expérience via les 'propagators' et les 'semi-lattices'"},
  {"uuid": "bb428226-6f01-2bf0-d36f-ae849d6f77cd", "date": "020F01",
    "duration": 60, "sector": "programming", "project": "orion",
    "label": "Implémentation du format de sérialisation"},
  {"uuid": "fe33a0e5-c0e3-f7d5-104a-e01fbc96d3d4", "date": "020E31",
    "duration": 200, "sector": "maintenance", "project": "rme",
    "label": "Préparation de la v3.0.0"},
  {"uuid": "41fc2e7d-8a39-2055-b4d6-9059a07e3ee4", "date": "020E30",
    "duration": 120, "sector": "research", "project": "orion",
    "label": "Définition d'une roadmap"},
  {"uuid": "4c7d63ac-facf-dad3-e488-57ca17aa1266", "date": "020E29",
    "duration": 320, "sector": "programming", "project": "orion",
    "label": "Expériences de parsing via Transept"},
  {"uuid": "f37fc2e9-17a6-940e-ad3b-f05790a7dfa9", "date": "020E28",
    "duration": 320, "sector": "programming", "project": "orion",
    "label": "Définition d'un format de sérialisation"},
  {"uuid": "cfd7a3c8-4c4e-81f5-14e4-db741cfec1f3", "date": "020E27",
    "duration": 200, "sector": "programming", "project": "orion",
    "label": "Expériences autours du parsing"},
  {"uuid": "72e58d7c-3f47-4fa4-398c-8919974a5f26", "date": "020E26",
    "duration": 200, "sector": "maintenance", "project": null,
    "label": "Configuration de ma machine personnelle (installation de logiciels manquants)"},
  {"uuid": "31e2fec5-1494-e90f-3603-f01d4075586e", "date": "020E26",
    "duration": 120, "sector": "programming", "project": "orion",
    "label": "Initialisation du projet"},
  {"uuid": "62e40868-c34e-2656-588a-b77a01ad7785", "date": "020E25",
    "duration": 320, "sector": "programming", "project": null,
    "label": "Expériences avec LablGTK"},
  {"uuid": "a6a9352a-42b8-b952-2106-db931b2e7bf9", "date": "020E24",
    "duration": 200, "sector": "programming", "project": null,
    "label": "Expériences avec LablGTK"},
  {"uuid": "31127c31-d8c9-209d-3689-242a19f20a3b", "date": "020E23",
    "duration": 320, "sector": "maintenance", "project": null,
    "label": "Installation et configuration de ma machine personnelle"},
  {"uuid": "1056e9aa-3d7a-07c8-ba9e-f838cdaf0d11", "date": "020E22",
    "duration": 450, "sector": "maintenance", "project": null,
    "label": "Reinstallation de ma machine personnelle"},
  {"uuid": "09b12804-5314-e484-7a2b-eea7c400c3fa", "date": "020E21",
    "duration": 450, "sector": "maintenance", "project": null,
    "label": "Sauvegarde des données importante de mon ordinateur en vue d'une mise à jour"},
  {"uuid": "608899ae-d1a5-0606-374f-cf2665d3e4df", "date": "020E20",
    "duration": 200, "sector": "maintenance", "project": null,
    "label": "Observation de différentes distributions Linux"},
  {"uuid": "46a21802-3c40-959c-5386-6444580ddf36", "date": "020E19",
    "duration": 450, "sector": "maintenance", "project": null,
    "label": "Sauvegarde des données sensibles de mon ordinateur"},
  {"uuid": "3243b07d-f88c-ebd6-fba6-54bc4e89f831", "date": "020E18",
    "duration": 220, "sector": "research", "project": null,
    "label": "Expériences sur la creation d'un framework reactif en OCaml"},
  {"uuid": "3c9bb52c-b616-8a3b-fa16-2a2dbeee9ee8", "date": "020E17",
    "duration": 400, "sector": "programming", "project": "rme",
    "label": "Implémentation de la version 3.0.0 "},
  {"uuid": "2227880b-aa53-6683-79cf-d3bc88a91f4d", "date": "020E16",
    "duration": 120, "sector": "maintenance", "project": "rme",
    "label": "Selection des fonctionnalitées pour RME 3.0.0 "},
  {"uuid": "d66bb76d-36a8-5c1f-1880-23cfd861b4c0", "date": "020E15",
    "duration": 500, "sector": "research", "project": null,
    "label": "Expériences autours de la création d'un framework frontend réactif en OCaml"},
  {"uuid": "1287adb7-dd3b-16ad-3154-524d114b70d2", "date": "020E14",
    "duration": 500, "sector": "research", "project": null,
    "label": "Expériences autours de la création d'un framework frontend réactif en OCaml"},
  {"uuid": "13a60be5-e278-f136-65cc-67f8e7930ddd", "date": "020E13",
    "duration": 200, "sector": "research", "project": null,
    "label": "Expériences autours de la création d'un framework frontend réactif en OCaml"},
  {"uuid": "93435140-0f81-f322-b3f3-23950963523c", "date": "020E12",
    "duration": 220, "sector": "research", "project": null,
    "label": "Expériences autours de la création d'un framework frontend réactif en OCaml"},
  {"uuid": "27f90e8d-d690-8cc7-a9a6-1f9b947cf730", "date": "020E11",
    "duration": 120, "sector": "research", "project": null,
    "label": "Expériences autours de la création d'un framework frontend réactif en OCaml"},
  {"uuid": "9315aa89-9c33-68ed-07f2-e5323cf3a594", "date": "020E10",
    "duration": 320, "sector": "research", "project": null,
    "label": "Expériences autours de la création d'un framework frontend réactif en OCaml"},
  {"uuid": "de274bff-157b-3a75-b77e-4c27a59c7217", "date": "020E09",
    "duration": 200, "sector": "research", "project": null,
    "label": "Expériences sur la construction d'un framework frontend réactif en OCaml"},
  {"uuid": "e88f23ce-1c02-3ace-27c8-c4cf83813b38", "date": "020E08",
    "duration": 30, "sector": "maintenance", "project": "planet",
    "label": "Reorganisation des tâches"},
  {"uuid": "f1ff2656-6f2c-2cad-d42d-2ab3be745fc0", "date": "020E07",
    "duration": 450, "sector": "writing", "project": null,
    "label": "Ecriture de la présentation sur les effets algébriques pour LambdaLille Remote 2"},
  {"uuid": "1c68acba-f235-995b-9bf6-d2d94e2bbe91", "date": "020E05",
    "duration": 230, "sector": "programming", "project": "preface",
    "label": "Amélioration des listes non-vides et ajout des monoïdes et semigroupes paramétrés"},
  {"uuid": "064d7460-d18e-0706-7747-3390c849b3ac", "date": "020E04",
    "duration": 320, "sector": "research", "project": null,
    "label": "Amélioration de la présentation sur les effets (LambdaLille)"},
  {"uuid": "1418a699-ec3a-b2df-e6b6-8fc5f9f73326", "date": "020E03",
    "duration": 120, "sector": "programming", "project": "preface",
    "label": "Implémentation des tests unitaires (listes non-vides, semigroupes et monoïdes)"},
  {"uuid": "82087fa5-fbde-1c93-2651-2d9a26683484", "date": "020E02",
    "duration": 320, "sector": "programming", "project": "preface",
    "label": "Implémentation des listes non-vides, des semigroupes et des monoïdes"},
  {"uuid": "8cb7c7cf-92f2-3377-4530-9cb23d7500cd", "date": "020E01",
    "duration": 120, "sector": "programming", "project": "preface",
    "label": "Expérience sur les monoïdes et les semigroupes"},
  {"uuid": "1e7bfdab-9bee-716c-07b5-efe751b67501", "date": "020D30",
    "duration": 40, "sector": "maintenance", "project": "preface",
    "label": "Fusion et gestion de branches"},
  {"uuid": "43467e47-a477-9981-bb30-073ccac7ec06", "date": "020D29",
    "duration": 120, "sector": "writing", "project": "planet",
    "label": "Finalisation de l'article sur les extensions"},
  {"uuid": "ed7a5567-28c3-521c-0bb7-c0ceaeb36016", "date": "020D28",
    "duration": 160, "sector": "writing", "project": "planet",
    "label": "Rédaction de l'article sur les extensions"},
  {"uuid": "2c71269d-7669-6082-5e90-21b7b782706b", "date": "020D27",
    "duration": 120, "sector": "writing", "project": "planet",
    "label": "Initialisation de l'article sur les extensions en Kotlin"},
  {"uuid": "464348e4-d05b-3f05-2bf0-e9c40b336a05", "date": "020D24",
    "duration": 200, "sector": "programming", "project": "preface",
    "label": "Expériences sur Arrow/Apply/Choice (et Selective)"},
  {"uuid": "b19cf16a-7ec6-065b-2606-500d3a4e3051", "date": "020D21",
    "duration": 60, "sector": "research", "project": "preface",
    "label": "Expériences à l'utilisation de Preface"},
  {"uuid": "a3eeda4e-aa3f-6c23-cbbf-d79c70387cc4", "date": "020D20",
    "duration": 120, "sector": "research", "project": "preface",
    "label": "Expérience avec Preface pour la construction de logiciels"},
  {"uuid": "80f0d419-3193-fd99-457e-80c5213c1ac5", "date": "020D19",
    "duration": 450, "sector": "writing", "project": null,
    "label": "Ecriture du talk 'effets' pour LambdaLille"},
  {"uuid": "47430633-0136-8281-6ef7-6442bc86afe9", "date": "020D18",
    "duration": 200, "sector": "research", "project": "preface",
    "label": "Lecture Arrow/Choice/Apply"},
  {"uuid": "3eb480af-11ce-a438-1af7-e52338346120", "date": "020D17",
    "duration": 320, "sector": "research", "project": "preface",
    "label": "Expériences dans la création de logiciel avec Preface"},
  {"uuid": "aab77a76-9bf7-03e9-c2b3-b053714e53e8", "date": "020D16",
    "duration": 120, "sector": "research", "project": "preface",
    "label": "Relecture de patch (Tests, State)"},
  {"uuid": "ffd97355-f85c-48a3-6ecd-865cf1bfd7b9", "date": "020D15",
    "duration": 320, "sector": "research", "project": "preface",
    "label": "Expériences d'utilisation de Preface dans un projet concret"},
  {"uuid": "a09c2f88-8b2c-0127-ad11-4c36f15b5911", "date": "020D14",
    "duration": 120, "sector": "research", "project": "preface",
    "label": "Expériences avec Preface (Free/Freer)"},
  {"uuid": "e96ea8b9-6e4c-b6fb-d6d9-661493ce2670", "date": "020D13",
    "duration": 60, "sector": "programming", "project": "preface",
    "label": "Enrichissement de l'API de Stream"},
  {"uuid": "7c071f8e-4d62-721d-525b-bd7c396c0ca2", "date": "020D12",
    "duration": 60, "sector": "programming", "project": "preface",
    "label": "Enrichissement de l'API de Stream"},
  {"uuid": "2aef6c27-cc34-6b95-6da6-e30d0905472d", "date": "020D10",
    "duration": 120, "sector": "programming", "project": "preface",
    "label": "Expériences avec les comonades et les streams"},
  {"uuid": "4b408c2f-d1c7-d5ce-fdb6-fe7c846ccbd5", "date": "020D08",
    "duration": 35, "sector": "programming", "project": "preface",
    "label": "Enrichissement de l'API des Streams"},
  {"uuid": "b941bf00-23ea-0a27-0e66-24e9add88cfd", "date": "020D07",
    "duration": 120, "sector": "research", "project": "preface",
    "label": "Relecture de l'intégration de QCheck pour vérifier les lois"},
  {"uuid": "f0ed53ea-2762-5360-1849-187f845098d4", "date": "020D06",
    "duration": 120, "sector": "maintenance", "project": "preface",
    "label": "Revue des premiers tests dirigés par les propriétés"},
  {"uuid": "7d219b8e-78a5-f8d5-a239-d38bb073dce3", "date": "020D05",
    "duration": 320, "sector": "programming", "project": "planet",
    "label": "Expériences sur la version 2 "},
  {"uuid": "1d216b4a-447f-1aef-75ce-8a4c4d7f6da8", "date": "020D04",
    "duration": 120, "sector": "research", "project": "preface",
    "label": "Expériences autour des foncteurs selectifs applicatifs"},
  {"uuid": "cc08450d-4604-6ec5-0873-40de85d4034a", "date": "020D03",
    "duration": 120, "sector": "research", "project": "preface",
    "label": "Expériences d'utilisation de Preface dans Planet"},
  {"uuid": "f2f51490-bd13-13d0-4673-f7a5e80df35d", "date": "020D02",
    "duration": 30, "sector": "research", "project": "preface",
    "label": "Relecture de l'intégration de Either (avec un Bifoncteur)"},
  {"uuid": "03730d5d-0a9f-a367-dd94-64763882af5a", "date": "020C31",
    "duration": 120, "sector": "research", "project": "preface",
    "label": "Expériences sur les modules et la construction de foncteurs à deux paramètres"},
  {"uuid": "45e65170-6148-4940-2228-8d66ad201c49", "date": "020C30",
    "duration": 60, "sector": "research", "project": "preface",
    "label": "Expériences sur les modules et la construction de foncteurs à deux paramètres"},
  {"uuid": "80c29e73-6074-6ae1-86d9-53f7b5108b81", "date": "020C29",
    "duration": 85, "sector": "visual", "project": "planet",
    "label": "Legers correctifs temporaires sur la version responsive"},
  {"uuid": "e8d3d58f-e106-27d4-0c9f-431ef6de57e7", "date": "020C27",
    "duration": 30, "sector": "maintenance", "project": "preface",
    "label": "Quelques petits correctifs (typo et nommage)"},
  {"uuid": "3373f5f5-f641-b732-a9ca-c1a36e6ba8f4", "date": "020C24",
    "duration": 120, "sector": "programming", "project": "preface",
    "label": "Expérimentation d'une nouvelle organisation"},
  {"uuid": "7a5ce0c9-360b-a56e-a27d-9d4f52413d80", "date": "020C22",
    "duration": 30, "sector": "maintenance", "project": "preface",
    "label": "Revue de Continuation"},
  {"uuid": "ff0510ac-6547-0392-92ae-b55322316a4e", "date": "020C15",
    "duration": 20, "sector": "maintenance", "project": "planet",
    "label": "Correctif de l'article sur les effets"},
  {"uuid": "03ca2dc1-39c9-848b-e954-95b62372d9c6", "date": "020C12",
    "duration": 60, "sector": "maintenance", "project": "planet",
    "label": "Corrections et précisions de l'article sur les effets"},
  {"uuid": "a9592aa2-0027-7e64-5e18-6ea2467f2625", "date": "020C11",
    "duration": 60, "sector": "maintenance", "project": "planet",
    "label": "Correction et remerciements de l'article sur les effets"},
  {"uuid": "d453e17a-aa56-9d94-a1df-efdf0253f2b6", "date": "020C11",
    "duration": 60, "sector": "research", "project": null,
    "label": "Expériences avec Eff"},
  {"uuid": "0e330f29-3a3b-0466-93e3-87967b803357", "date": "020C10",
    "duration": 220, "sector": "writing", "project": "planet",
    "label": "Progression sur l'article à propos des effets algébriques"},
  {"uuid": "a7b9b955-49bc-ec0a-1722-8896cf1ad688", "date": "020C09",
    "duration": 320, "sector": "writing", "project": "planet",
    "label": "Avancées sur l'articles à propos des effets algébriques"},
  {"uuid": "ff39e8ba-4d91-df29-054d-ea5bbeb1334b", "date": "020C08",
    "duration": 200, "sector": "research", "project": "planet",
    "label": "Effets algébriques et leurs gestionnaires, expériences avec Koka"},
  {"uuid": "b3e12b8e-2649-2a67-199d-a19a6111d4ff", "date": "020C06",
    "duration": 300, "sector": "writing", "project": "planet",
    "label": "Avancée sur l'article des effets algébriques"},
  {"uuid": "91aa66df-8a6f-2e22-f0f2-e26aed44d84c", "date": "020C05",
    "duration": 320, "sector": "writing", "project": "planet",
    "label": "Articles sur les effets algébriques et les tests unitaires"},
  {"uuid": "cb9e079c-3a94-63e4-4b39-ed93a5906402", "date": "020C04",
    "duration": 120, "sector": "writing", "project": "planet",
    "label": "Article sur les effets algébriques et les tests unitaires"},
  {"uuid": "1b457823-905c-3e38-a5ba-89436cc44040", "date": "020C02",
    "duration": 320, "sector": "writing", "project": "planet",
    "label": "Rédaction d'un article sur les effets et leurs gestionnaires"},
  {"uuid": "954a2b88-1b2d-cfc4-0270-805415fbec83", "date": "020B28",
    "duration": 120, "sector": "writing", "project": "planet",
    "label": "Initialisation d'un article sur les effets algébriques"},
  {"uuid": "80ad9b1e-c9a9-3cf5-3e44-4202c8d4c5a9", "date": "020B27",
    "duration": 320, "sector": "writing", "project": null,
    "label": "Finalisation du talk sur les effets pour le GDG"},
  {"uuid": "83fb3ae2-dbd9-a4dc-15c1-6bcf5ec4eda3", "date": "020B25",
    "duration": 300, "sector": "research", "project": null,
    "label": "Préparation du talk sur les effets pour le GDG"},
  {"uuid": "0a619fc2-174e-4f1e-ae01-6f2c8b9541a9", "date": "020B25",
    "duration": 600, "sector": "writing", "project": null,
    "label": "Ecriture du talk sur les effets pour le GDG"},
  {"uuid": "f19ab90e-9347-b0ff-63b3-d026dda715a1", "date": "020B24",
    "duration": 320, "sector": "writing", "project": null,
    "label": "Ecriture du talk sur les gestionnaires d'effets en programmation fonctionnelle"},
  {"uuid": "4c2cdada-7a80-2374-d06d-56f04d4bb07e", "date": "020B23",
    "duration": 320, "sector": "research", "project": null,
    "label": "Recherches et expériences sur les gestionnaires d'effets"},
  {"uuid": "821f4af0-e7fc-d27a-d7d3-5b5aa8447f22", "date": "020B22",
    "duration": 320, "sector": "writing", "project": null,
    "label": "Ecriture du talk sur les gestionnaires d'effets en programmation fonctionnelle"},
  {"uuid": "d81c21aa-c48f-0d20-b685-450dd98cf15c", "date": "020B21",
    "duration": 200, "sector": "research", "project": null,
    "label": "Recherches et expériences sur les gestionnaires d'effets"},
  {"uuid": "a2629c5f-ddd2-35e9-3922-7981b9b5e8ca", "date": "020B20",
    "duration": 200, "sector": "writing", "project": null,
    "label": "Ecriture du talk sur les gestionnaires d'effets en programmation fonctionnelle"},
  {"uuid": "9a8aa22c-175f-2c4d-52fc-c7fe1f8a8d8e", "date": "020B19",
    "duration": 120, "sector": "research", "project": null,
    "label": "Recherches et expérimentations sur les gestionnaires d'effets"},
  {"uuid": "8c21884c-ff86-331c-46f3-160c7211958c", "date": "020B18",
    "duration": 120, "sector": "research", "project": null,
    "label": "Recherches et expérimentations sur les systèmes d'effets"},
  {"uuid": "58eb909e-b1a4-29ab-59c9-05d7643d6d6a", "date": "020B17",
    "duration": 600, "sector": "research", "project": null,
    "label": "Recherches et expérimentations variées sur les modules, les effets et les flèches"},
  {"uuid": "9a74d2eb-f803-7b02-6292-9c923f0bcc26", "date": "020B15",
    "duration": 320, "sector": "programming", "project": "diarium",
    "label": "Initiation du projet et organisation du dépôt"},
  {"uuid": "3d3b8c8b-ddbc-bc58-eec5-6005eeac9753", "date": "020B15",
    "duration": 45, "sector": "maintenance", "project": "preface",
    "label": "Utilisation des actions Github OCaml"},
  {"uuid": "3b31f556-e8d7-156b-e863-98ea1c3e2437", "date": "020B15",
    "duration": 45, "sector": "programming", "project": "diarium",
    "label": "Initiation du module Unix"},
  {"uuid": "a37c5396-0103-dac2-00b4-b227f2e2b7f4", "date": "020B13",
    "duration": 120, "sector": "maintenance", "project": null,
    "label": "Maintenance des paquets jsoo_storage et jsoo_broadcastchannel"},
  {"uuid": "63b724d7-ae90-16b8-41b4-7eb0eda3fd52", "date": "020B13",
    "duration": 60, "sector": "visual", "project": null,
    "label": "Illustrations variées (et ratées)"},
  {"uuid": "bc38dda4-2807-5680-8881-bd7443e36004", "date": "020B13",
    "duration": 60, "sector": "maintenance", "project": null,
    "label": "Correctif des dépendances de jsoo_broadcastchannel et jsoo_storage"},
  {"uuid": "767e65ac-86f1-9a84-56dc-33980fd1837f", "date": "020B12",
    "duration": 60, "sector": "maintenance", "project": "planet",
    "label": "Amélioration de la définition de l'état par défaut des tâches"},
  {"uuid": "f5db755d-9b1e-3a49-fa03-2873330ec2bc", "date": "020B10",
    "duration": 200, "sector": "writing", "project": null,
    "label": "Progression de l'écriture du talk sur les effets"},
  {"uuid": "e91e0bb9-9b15-0c5e-c46d-32ad0883f2f2", "date": "020B09",
    "duration": 320, "sector": "writing", "project": null,
    "label": "Rédaction du script de la présentation sur les effets"},
  {"uuid": "4c807cd4-ffe5-e416-f1c8-0a0874afcc0c", "date": "020A31",
    "duration": 120, "sector": "visual", "project": "planet",
    "label": "Intégration des galeries dans l'application web"},
  {"uuid": "4e434e59-ed41-96be-bb87-152369a42076", "date": "020A31",
    "duration": 30, "sector": "programming", "project": "planet",
    "label": "Intégration des galeries dans les tags"},
  {"uuid": "057f63f7-12e3-17f9-1545-119fb3818367", "date": "020A30",
    "duration": 20, "sector": "maintenance", "project": "planet",
    "label": "Correctif du build Hakyll"},
  {"uuid": "1bfafb3f-cd55-1bf5-4447-a2f88838b7bf", "date": "020A30",
    "duration": 30, "sector": "visual", "project": "planet",
    "label": "Légère modification visuelle pour les tags"},
  {"uuid": "8e78b66e-89a9-b8ca-7c68-e868fe84af4d", "date": "020A29",
    "duration": 60, "sector": "programming", "project": "planet",
    "label": "Intégration des galeries dans le processus de compilation"},
  {"uuid": "f09ba1d3-f69f-7ccc-7222-a89797211447", "date": "020A28",
    "duration": 10, "sector": "programming", "project": "preface",
    "label": "Correctif pour les Traversables"},
  {"uuid": "46c7a76d-8339-9d06-f0f6-ddbff33384fa", "date": "020A28",
    "duration": 30, "sector": "programming", "project": "planet",
    "label": "Génération des artefacts Hakyll pour les galeries"},
  {"uuid": "20411c0b-549d-9c3a-8b61-d83189913451", "date": "020A26",
    "duration": 200, "sector": "programming", "project": "planet",
    "label": "Progrès sur les galeries internes"},
  {"uuid": "f6d752b2-d937-a118-b498-5a000d6a72c6", "date": "020A26",
    "duration": 120, "sector": "programming", "project": "planet",
    "label": "Amélioration des binaires de génération de galeries"},
  {"uuid": "4f1a97e8-8d34-f2f9-826f-e532f77d2bcd", "date": "020A25",
    "duration": 30, "sector": "programming", "project": "planet",
    "label": "Initialisation du modèle des images pour les galeries"},
  {"uuid": "f76de290-bb4c-531f-5b2c-e17ef5d0703f", "date": "020A25",
    "duration": 60, "sector": "programming", "project": "planet",
    "label": "Implémentation des galeries"},
  {"uuid": "58e02b83-9fb1-c8a3-9f6c-993a65abee04", "date": "020A24",
    "duration": 120, "sector": "visual", "project": null,
    "label": "Quelques croquis en noir et blanc (non conservés pour la majeure partie...)"},
  {"uuid": "28f6566c-12a5-f952-8405-33ecaec363d8", "date": "020A23",
    "duration": 120, "sector": "programming", "project": "preface",
    "label": "Documentation et test pour Validation et Try"},
  {"uuid": "e7902b13-bb47-8bae-c93c-096a4ad6afeb", "date": "020A22",
    "duration": 120, "sector": "programming", "project": "preface",
    "label": "Implémentation des modules Try et Validation et amélioration des tests"},
  {"uuid": "e98243ca-5a13-a32b-1551-37e13b870daf", "date": "020A22",
    "duration": 180, "sector": "programming", "project": "preface",
    "label": "Documentation et test pour Traversable, List, Try et Validation"},
  {"uuid": "878dc9b2-44cb-85b5-4aa6-0f339554e3c7", "date": "020A21",
    "duration": 20, "sector": "visual", "project": "planet",
    "label": "Légère modification des couleurs et de l'UI"},
  {"uuid": "f3d81d05-01e4-a8f9-0cc6-23378eaaff42", "date": "020A20",
    "duration": 120, "sector": "programming", "project": "preface",
    "label": "Implémentation des traversables"},
  {"uuid": "f5ad590c-5adc-36bf-952f-fa17cb3e83d4", "date": "020A17",
    "duration": 10, "sector": "visual", "project": "rme",
    "label": "Création du Pictogramme"},
  {"uuid": "b9e75f1a-3d0c-9f73-7b6d-4dac2ab5bb96", "date": "020A17",
    "duration": 120, "sector": "writing", "project": "rme",
    "label": "Rédaction de la présentation"},
  {"uuid": "744c8cf0-be0f-45a4-78e5-89eb641b003f", "date": "020A15",
    "duration": 120, "sector": "maintenance", "project": "rme",
    "label": "Correction pour l'implémentation des boucles et amélioration des retours d'erreur"},
  {"uuid": "7c18368e-415a-a552-77fe-667de00f77ec", "date": "020A11",
    "duration": 300, "sector": "programming", "project": "rme",
    "label": "Implémentation de commandes pour la version 2.1.0"},
  {"uuid": "ff8c4c4d-d3c0-88b6-f840-a82d9664c7f0", "date": "020A11",
    "duration": 200, "sector": "maintenance", "project": "rme",
    "label": "Correctifs de bogues sur RME 2.1.0"},
  {"uuid": "4bf434df-8499-2532-cd9a-c283cfa23810", "date": "020A11",
    "duration": 120, "sector": "programming", "project": "rme",
    "label": "Implémentation des boucles dans le DSL"},
  {"uuid": "d9c3a14f-fa9f-a7d5-33c6-917c095e09c0", "date": "020A10",
    "duration": 15, "sector": "programming", "project": "planet",
    "label": "Ajout du projet dans la liste des tâches"},
  {"uuid": "e6768506-123c-04c9-2fba-50644f033de2", "date": "020A10",
    "duration": 30, "sector": "maintenance", "project": "rme",
    "label": "Choix des fonctionnalités à implémenter pour la version 2.1.0 de RME"},
  {"uuid": "fef35b9e-9851-4d79-cf73-9c894801865b", "date": "020A09",
    "duration": 340, "sector": "visual", "project": "planet",
    "label": "Interface graphique (et implémentation) de l'affichage des tâches"},
  {"uuid": "26ed5b37-63d4-1e88-2fc1-62987bc3af36", "date": "020A08",
    "duration": 120, "sector": "programming", "project": "planet",
    "label": "Sérialisation des tâches en JSON et intégration dans la routine de construction"},
  {"uuid": "33726ef3-2df0-8391-109a-31f5d0b039cc", "date": "020A06",
    "duration": 300, "sector": "programming", "project": "planet",
    "label": "Checklist de la todo-list modifiable"},
  {"uuid": "34ce642c-878b-0e3a-8462-39577fe46b1a", "date": "020A06",
    "duration": 30, "sector": "visual", "project": "planet",
    "label": "Légère réorganisation des pages (localisation/activité)"},
  {"uuid": "714bd325-4365-5abc-3a86-ec3724538e92", "date": "020A05",
    "duration": 120, "sector": "programming", "project": "planet",
    "label": "Progrès sur le gestionnaire de tâches"},
  {"uuid": "a373582c-88f0-c9b0-dd2e-6ded2647b8d8", "date": "020A05",
    "duration": 320, "sector": "research", "project": null,
    "label": "Réunion de matériel pour 'la chimère fragile'"},
  {"uuid": "e9f9a870-e9f3-1c78-f97b-749c5a3865ef", "date": "020A01",
    "duration": 200, "sector": "programming", "project": "planet",
    "label": "Initiation des tâches de la todo-list"},
  {"uuid": "c37b5bab-adeb-65b5-a426-196893e03fb1", "date": "019L30",
    "duration": 200, "sector": "programming", "project": "planet",
    "label": "Mise à jours des tâches (création)"},
  {"uuid": "4d374625-4437-0fc1-1182-8483cc35b622", "date": "019L28",
    "duration": 5, "sector": "maintenance", "project": "planet",
    "label": "Mise à jours des dépendances"},
  {"uuid": "29724761-929a-0b89-f668-4cf1fbfa5ed0", "date": "019L28",
    "duration": 80, "sector": "programming", "project": "planet",
    "label": "Progression dans la construction de tâches"},
  {"uuid": "0ad56ef5-e68c-b7c9-8609-092048d0aa0d", "date": "019L26",
    "duration": 200, "sector": "research", "project": null,
    "label": "Recherches sur l'analyse structurale du récit, lecture de 'Communication 8'"},
  {"uuid": "90e842ad-3117-4dfb-82e8-5aa2bc611ddf", "date": "019L25",
    "duration": 200, "sector": "research", "project": null,
    "label": "Recherches sur l'analyse structurale du récit, lecture de 'Communication 8'"},
  {"uuid": "ce01d1b5-8d11-25cc-e4bb-9d95be693a36", "date": "019L24",
    "duration": 200, "sector": "research", "project": null,
    "label": "Recherches sur l'analyse structurale du récit, lecture de 'Communication 8'"},
  {"uuid": "a731574b-343b-b5df-edd0-f075e6b5c087", "date": "019L23",
    "duration": 120, "sector": "research", "project": null,
    "label": "Recherches sur l'analyse structurale du récit, lecture de 'Communication 8'"},
  {"uuid": "df3b2071-d81f-0b1c-6f47-da7b24a4c73a", "date": "019L20",
    "duration": 30, "sector": "programming", "project": "planet",
    "label": "Implémentation de la saisie de tâches"},
  {"uuid": "a86782bc-c5c2-8017-6dcb-227f91dd16d1", "date": "019L19",
    "duration": 120, "sector": "research", "project": "planet",
    "label": "Recherche et correctifs pour la hauteur de viewport sur Safari"},
  {"uuid": "7f034cb9-d198-90a8-896f-27d29276b7ec", "date": "019L19",
    "duration": 60, "sector": "programming", "project": "planet",
    "label": "Sérialisation, désérialisation des tâches"},
  {"uuid": "4c4d7c4a-85f5-9630-d8fd-efcacef39a34", "date": "019L19",
    "duration": 200, "sector": "programming", "project": "planet",
    "label": "Implémentation des tâches (Json et glue)"},
  {"uuid": "885accc4-c4a1-da27-2f67-e746ef1ed28a", "date": "019L16",
    "duration": 60, "sector": "programming", "project": "preface",
    "label": "Implémentation, documentation et test du module Option"},
  {"uuid": "f3c9d983-8dc1-6be6-88e4-0b6cf7fdb858", "date": "019L16",
    "duration": 30, "sector": "programming", "project": "planet",
    "label": "Page aléatoire dans le footer"},
  {"uuid": "bd96e070-0d6a-5fe5-359f-e8bbb79d286a", "date": "019L14",
    "duration": 120, "sector": "programming", "project": "planet",
    "label": "Finalisation des tags interactifs"},
  {"uuid": "6f47b9fc-a159-1778-74fb-bc0bf9a39d20", "date": "019L14",
    "duration": 5, "sector": "programming", "project": "planet",
    "label": "Ajout d'un wildcard pour les tags"},
  {"uuid": "d1193914-87d7-85f6-287f-8f74393ef79f", "date": "019L13",
    "duration": 30, "sector": "maintenance", "project": "planet",
    "label": "Modification des paramètres de ocamlformat"},
  {"uuid": "e9ab00bd-e0d3-6d74-4865-e0ba755d3fbe", "date": "019L13",
    "duration": 150, "sector": "programming", "project": "planet",
    "label": "Intégration des tags interactifs"},
  {"uuid": "04232a35-65f2-c5f9-4f10-6ad0208cc732", "date": "019L05",
    "duration": 45, "sector": "programming", "project": "preface",
    "label": "Reorganisation de l'anatomie de la bibliothèque"},
  {"uuid": "1d920614-f1d8-0075-cdf1-8db70cd1c76b", "date": "019L05",
    "duration": 30, "sector": "programming", "project": "preface",
    "label": "Modularisation des tests unitaires"},
  {"uuid": "873f1e09-c4a8-0d72-cd89-c7cad2469c2d", "date": "019K29",
    "duration": 30, "sector": "research", "project": "preface",
    "label": "Relecture des différentes PR"},
  {"uuid": "ea1ff422-adfe-e9b5-c4e7-5c57e3faf6dd", "date": "019K29",
    "duration": 5, "sector": "writing", "project": null,
    "label": "Correction d'un article"},
  {"uuid": "d5a74ca5-fa4b-bb9b-703a-50e7216e3b31", "date": "019K28",
    "duration": 40, "sector": "research", "project": "preface",
    "label": "Relecture des différentes PR"},
  {"uuid": "d5607227-3c08-0feb-a9dc-5ed74dd306ad", "date": "019K27",
    "duration": 30, "sector": "research", "project": "preface",
    "label": "Relecture des différentes PR"},
  {"uuid": "dc4f5126-3726-f9eb-50f6-100d0dd093b6", "date": "019K22",
    "duration": 400, "sector": "visual", "project": null,
    "label": "Cartographie vectorielle"},
  {"uuid": "847e4a79-47af-40dc-47a4-bc5b2798e3f7", "date": "019K21",
    "duration": 10, "sector": "maintenance", "project": "planet",
    "label": "Correctifs rapide sur la page d'accueil"},
  {"uuid": "0e70f52e-383f-5fe9-1926-dd59f5f4752c", "date": "019K19",
    "duration": 200, "sector": "research", "project": null,
    "label": "Types existentiels et GADTs"},
  {"uuid": "d7a91529-2491-7e7c-647a-973ff44aaf4f", "date": "019K16",
    "duration": 200, "sector": "programming", "project": "planet",
    "label": "Finalisation du gestionnaire de TWTXT"},
  {"uuid": "3abe1b4d-b239-b2d2-181c-b4d453a5d611", "date": "019K15",
    "duration": 120, "sector": "programming", "project": "planet",
    "label": "Initialisation du publieur TWTXT"},
  {"uuid": "a4dabf5c-5f32-c8d8-4208-8e8fcc90cdc0", "date": "019K14",
    "duration": 10, "sector": "visual", "project": "planet",
    "label": "Légères modifications sur l'interface graphique"},
  {"uuid": "fcea56c0-3f78-bda0-2249-0bee1f327d78", "date": "019K13",
    "duration": 60, "sector": "maintenance", "project": null,
    "label": "Amélioration de mon Bashprofile"},
  {"uuid": "7cafbe25-12ef-aef2-22cc-5d4daa727a45", "date": "019K13",
    "duration": 60, "sector": "programming", "project": "planet",
    "label": "Ajout des mises à jours de la platforme"},
  {"uuid": "269288a4-cce3-03b0-9475-fa3008ff5fb6", "date": "019K13",
    "duration": 30, "sector": "visual", "project": "planet",
    "label": "Légères modifications de l'UI"},
  {"uuid": "06b9c384-5335-ab90-a4ea-56fc2c63b733", "date": "019K10",
    "duration": 320, "sector": "research", "project": null,
    "label": "Expériences photographiques"},
  {"uuid": "fa9e1f44-7c17-c43b-7773-c271c98e013d", "date": "019K09",
    "duration": 320, "sector": "research", "project": null,
    "label": "Expériences photographiques"},
  {"uuid": "bf603dcc-d361-63a7-5dba-74cdf080f2cf", "date": "019K08",
    "duration": 120, "sector": "writing", "project": "planet",
    "label": "Ecriture de l'article sur le Kata du tennis appliqué à OCaml"},
  {"uuid": "eb7b1777-af15-64d3-b65d-34406af0a128", "date": "019K08",
    "duration": 200, "sector": "research", "project": null,
    "label": "Expériences photographiques"},
  {"uuid": "d2a4d3d2-4b89-427c-18a8-4767bb798c63", "date": "019K07",
    "duration": 200, "sector": "writing", "project": "planet",
    "label": "Démarrage de l'article sur le Kata du tennis en OCaml"},
  {"uuid": "ade24056-7763-794e-ee2c-200bf1d22708", "date": "019J31",
    "duration": 600, "sector": "research", "project": null,
    "label": "Conférence, ScalaIO 2019"},
  {"uuid": "967681a5-bf1c-cfc8-f34f-03aea6741ee1", "date": "019J30",
    "duration": 600, "sector": "research", "project": null,
    "label": "Conférence, ScalaIO 2019"},
  {"uuid": "72c1f185-2ed2-d241-0b23-5c11f023bc73", "date": "019J29",
    "duration": 600, "sector": "research", "project": null,
    "label": "Conférence, ScalaIO 2019"},
  {"uuid": "c3cb8fca-c0af-293a-0e91-2a35cf9ab073", "date": "019J27",
    "duration": 200, "sector": "programming", "project": "rme",
    "label": "Implémentation d'une boucle de feedback pour les erreurs"},
  {"uuid": "009e37e8-10f9-3f8a-1cf4-7c36e11c9b13", "date": "019J24",
    "duration": 60, "sector": "visual", "project": "planet",
    "label": "Amélioration du layout pour la reprise des articles"},
  {"uuid": "929f79fa-7f15-462f-072a-a8a2795931b9", "date": "019J24",
    "duration": 20, "sector": "programming", "project": "planet",
    "label": "Liens des articles cliquables"},
  {"uuid": "47ed7b89-f73e-67fc-704e-4688872d2b7a", "date": "019J20",
    "duration": 120, "sector": "programming", "project": "planet",
    "label": "Amélioration de ROE pour préserver le formattage babel de Org"},
  {"uuid": "81fbbd28-a35c-055c-9e0d-633957f37ac2", "date": "019J20",
    "duration": 60, "sector": "visual", "project": "planet",
    "label": "Rendu, un peu pauvre, des pages mobiles"},
  {"uuid": "e7c69553-5eeb-1ced-2c39-601911e91175", "date": "019J20",
    "duration": 30, "sector": "visual", "project": "planet",
    "label": "Modification de la page d'accueil et alignement des blocs"},
  {"uuid": "548651cc-d170-c5a5-7139-a7ce4d21ae6e", "date": "019J20",
    "duration": 20, "sector": "programming", "project": "planet",
    "label": "Ajout d'un fil de syndication Atom"},
  {"uuid": "f9f85b6c-51f1-87f8-ff01-ae1f24335917", "date": "019J20",
    "duration": 20, "sector": "programming", "project": "planet",
    "label": "Ajout d'un module de chargement pour les widget plus lourds"},
  {"uuid": "5477c557-c924-6539-48cc-aa86ca9d0006", "date": "019J19",
    "duration": 120, "sector": "visual", "project": null,
    "label": "Expériences avec Blender"},
  {"uuid": "3fa35daa-1f13-e97d-3c5f-9bf2b8b6aa1e", "date": "019J16",
    "duration": 30, "sector": "visual", "project": "planet",
    "label": "Quelques modifications sur la page 'A propos'"},
  {"uuid": "fee21698-f33f-549a-4bc7-5305729d2f77", "date": "019J16",
    "duration": 10, "sector": "maintenance", "project": "planet",
    "label": "Correction quotes/doublequotes"},
  {"uuid": "2fa1baa0-0dd3-d6c7-55e2-3a9ee77289f8", "date": "019J15",
    "duration": 60, "sector": "writing", "project": "planet",
    "label": "Rédaction de la page de présentation"},
  {"uuid": "b8608ddf-e4cf-1d9f-a457-bc4e746d49fc", "date": "019J09",
    "duration": 320, "sector": "programming", "project": "rme",
    "label": "Développement de la version 2"},
  {"uuid": "b7bdf7f7-cee0-4148-8ca3-83b95d05abde", "date": "019J02",
    "duration": 100, "sector": "programming", "project": "planet",
    "label": "Amélioration de l'interactivité dans le journal"},
  {"uuid": "500935cc-7393-8667-ae5e-b191b46b66db", "date": "019I26",
    "duration": 200, "sector": "programming", "project": "preface",
    "label": "Implémentation des monades dans la bibliothèque"},
  {"uuid": "16cae6dc-b80d-6fd9-025c-3d08a37bac31", "date": "019I26",
    "duration": 420, "sector": "programming", "project": "preface",
    "label": "Amélioration de l'API des monades"},
  {"uuid": "dfdcbd81-db07-9ae3-4a61-6512a4cec485", "date": "019I25",
    "duration": 60, "sector": "programming", "project": "preface",
    "label": "Initiation des monades dans la bibliothèque"},
  {"uuid": "17dc352a-d893-e299-db55-50e96e87272f", "date": "019I24",
    "duration": 30, "sector": "programming", "project": "preface",
    "label": "Relecture et expérimentation sur les Applicatives"},
  {"uuid": "c88119f9-d5c2-d224-991b-717ec2ef443c", "date": "019I23",
    "duration": 250, "sector": "visual", "project": "planet",
    "label": "Amélioration du visuel du journal"},
  {"uuid": "e7ea9479-8643-54d2-99a9-ce0ff7f029a4", "date": "019I23",
    "duration": 220, "sector": "programming", "project": "planet",
    "label": "Rendu interactif de la carte d'activité pour la page Journal"},
  {"uuid": "e0bbb18b-539a-0b85-36de-ece12d007e9f", "date": "019I22",
    "duration": 30, "sector": "visual", "project": "planet",
    "label": "Représentation des statistiques globales dans la page de Journal"},
  {"uuid": "ece79699-fe72-b72a-13b4-13180da5eea0", "date": "019I22",
    "duration": 30, "sector": "programming", "project": "preface",
    "label": "Modification de la représentation interne d'un Foncteur"},
  {"uuid": "bac96d41-ed75-adf9-b656-23855552998d", "date": "019I19",
    "duration": 60, "sector": "programming", "project": "planet",
    "label": "Isolation du code pour générer les statistiques par projets"},
  {"uuid": "8434002c-9e96-45ff-c6c7-191a287e5b9d", "date": "019I18",
    "duration": 200, "sector": "programming", "project": "planet",
    "label": "Helpers en tout genre pour les dates"},
  {"uuid": "48aa1634-c777-9ff2-5423-eb7ce55f74af", "date": "019I18",
    "duration": 300, "sector": "visual", "project": "planet",
    "label": "Expérience sur la représentation de calendriers"},
  {"uuid": "eb1df0a0-0d4c-7021-fbe0-d705dc47259b", "date": "019I18",
    "duration": 100, "sector": "programming", "project": "planet",
    "label": "Initiation de l'UI de la page Journal"},
  {"uuid": "db74d7c7-9a47-9215-0f8d-f92288d1229e", "date": "019I17",
    "duration": 45, "sector": "visual", "project": "planet",
    "label": "Affichage des positions dans la page location"},
  {"uuid": "55fe84d5-3e6a-a0ee-d883-dcee19e61efa", "date": "019I16",
    "duration": 120, "sector": "programming", "project": "planet",
    "label": "Développement d'un mode Emacs pour les tâches récurrentes"},
  {"uuid": "a529d6bb-47c0-4995-d3ca-989f3e4ca8bd", "date": "019I16",
    "duration": 180, "sector": "programming", "project": "planet",
    "label": "Affichages des locations dans une page dédiée"},
  {"uuid": "82194e5e-6ab2-36ef-1f2f-3d973af32299", "date": "019I14",
    "duration": 30, "sector": "programming", "project": "planet",
    "label": "Utilisation d'un contexte local pour la traversée des logs"},
  {"uuid": "d804224f-70ca-772f-3a37-34c02d816c1b", "date": "019I14",
    "duration": 60, "sector": "programming", "project": "planet",
    "label": "Récupération des données de localisation"},
  {"uuid": "597b5b43-6e19-b3eb-e23a-e64eefce49cd", "date": "019I14",
    "duration": 10, "sector": "writing", "project": "planet",
    "label": "Intégration de l'article Manben"},
  {"uuid": "fd752eb1-0acf-8e7d-b62b-4fd8872c9d8e", "date": "019I12",
    "duration": 120, "sector": "programming", "project": "planet",
    "label": "Intégration de la reprise de la lecture"},
  {"uuid": "520a73a5-1477-85ba-079f-929e8d5cdcf3", "date": "019I12",
    "duration": 100, "sector": "visual", "project": "planet",
    "label": "Page d'accueil adaptative"},
  {"uuid": "134b2a9c-bc59-aafa-9ef8-58aa2f4d576c", "date": "019I06",
    "duration": 60, "sector": "visual", "project": "planet",
    "label": "Amélioration de l'affichage des publications"},
  {"uuid": "48fcea64-8d93-34f4-4aea-24ba58a4f8f5", "date": "019I06",
    "duration": 60, "sector": "visual", "project": "planet",
    "label": "Amélioration de la page d'articles"},
  {"uuid": "8bb1194e-2f53-7bae-8588-f566669ec923", "date": "019I06",
    "duration": 20, "sector": "writing", "project": "planet",
    "label": "Actualisation de l'article sur les monades"},
  {"uuid": "7c77c97d-0b2f-75ed-3fe6-9c2931543d31", "date": "019I06",
    "duration": 30, "sector": "programming", "project": "planet",
    "label": "Ajout des liens en bas de page pour les articles"},
  {"uuid": "349a176a-1b84-1e0e-247c-b6c231fdced5", "date": "019I04",
    "duration": 320, "sector": "programming", "project": "planet",
    "label": "Génération des pages Hakyll en fonction des blog post"},
  {"uuid": "9766e842-e9ff-1cdc-95ac-a6e3c8b6e4aa", "date": "019I04",
    "duration": 60, "sector": "visual", "project": "planet",
    "label": "Mise en page de l'accueil du site"},
  {"uuid": "e5a1aa2a-bc43-f4c2-8cd8-a88e6aefbe32", "date": "019I03",
    "duration": 120, "sector": "programming", "project": "planet",
    "label": "Initialisation des stories. Ajout des blogposts"},
  {"uuid": "d9a59ee4-cc4d-702d-c270-adff3613f0a5", "date": "019I03",
    "duration": 30, "sector": "programming", "project": "planet",
    "label": "Dynamisation du copyright"},
  {"uuid": "75468218-2d53-fe5c-8196-f9a25c921750", "date": "019H29",
    "duration": 60, "sector": "programming", "project": "preface",
    "label": "Expériences avec le premier module"},
  {"uuid": "2b3c9dfa-af87-75fa-0eb1-0caa987cdf13", "date": "019H26",
    "duration": 30, "sector": "visual", "project": "brainfocaml",
    "label": "Dessin de la cover du projet"},
  {"uuid": "bbb064d1-273e-d31d-bdea-83a0d262728c", "date": "019H26",
    "duration": 300, "sector": "visual", "project": null,
    "label": "Dessins libres"},
  {"uuid": "c04d2ccf-1508-35d7-c4f8-285157e53262", "date": "019H25",
    "duration": 20, "sector": "writing", "project": "almost_heroic",
    "label": "Ecriture de la présentation pour Planet"},
  {"uuid": "d31de10d-1d82-7e05-8399-8ae6e2d3f5e1", "date": "019H25",
    "duration": 320, "sector": "maintenance", "project": "preface",
    "label": "Mise en place de l'intégration continue via les Github Actions"},
  {"uuid": "8839c7e9-d332-8ca9-c247-6f6bf956f44a", "date": "019H25",
    "duration": 30, "sector": "writing", "project": "brainfocaml",
    "label": "Présentation du projet pour Planet"},
  {"uuid": "89f522fc-c53d-bf71-0446-8c08ee8537d5", "date": "019H25",
    "duration": 60, "sector": "programming", "project": "brainfocaml",
    "label": "Refonte de l'API (utilisation de Dune, OCamlformat etc.)"},
  {"uuid": "64b5c2d9-442a-130b-f0ac-382c79e3314f", "date": "019H23",
    "duration": 200, "sector": "programming", "project": "preface",
    "label": "Initiation de l'infrastructure du projet"},
  {"uuid": "e91d9018-bdb3-83ea-eec0-13f088dd8041", "date": "019H23",
    "duration": 10, "sector": "visual", "project": "quasar",
    "label": "Création d'un pictogramme"},
  {"uuid": "bedbd840-314f-70c2-368e-95534d31f05d", "date": "019H23",
    "duration": 10, "sector": "visual", "project": "brainfocaml",
    "label": "Création d'un pictogramme"},
  {"uuid": "447159ba-a480-2eb5-af97-c76af5d30524", "date": "019H23",
    "duration": 15, "sector": "visual", "project": "qian",
    "label": "Nouveau pictogramme"},
  {"uuid": "93b7154f-463d-746c-e5fc-d0ecb76fe908", "date": "019H22",
    "duration": 30, "sector": "programming", "project": "preface",
    "label": "Initiation du projet"},
  {"uuid": "98b2688c-b374-41db-33ec-85355b8dded6", "date": "019H21",
    "duration": 120, "sector": "programming", "project": "planet",
    "label": "Amélioration de l'API JS de Planet et ajout de pastille de modifications"},
  {"uuid": "9d264552-0df4-ad7f-dfd5-b029bbe5ee2c", "date": "019H21",
    "duration": 100, "sector": "programming", "project": "planet",
    "label": "Remontée de la durée de vie du projet et amélioration de la génération des tables de mises à jours"},
  {"uuid": "3b2e6318-508f-00b1-5299-08efd73ee1a1", "date": "019H21",
    "duration": 120, "sector": "programming", "project": "planet",
    "label": "Expérimentations sur la mise en cache"},
  {"uuid": "dddeac9e-4c92-22b7-8b24-4655f3518896", "date": "019H21",
    "duration": 320, "sector": "maintenance", "project": "planet",
    "label": "Amélioration (et fragmentation) du code"},
  {"uuid": "e84c983c-d866-437c-5a99-9d4063c7a99d", "date": "019H20",
    "duration": 20, "sector": "programming", "project": "planet",
    "label": "Ajout d'un block relatif aux dépôt des projets"},
  {"uuid": "c2a0dcd7-a9de-33bb-ecc6-ef684d755241", "date": "019H19",
    "duration": 120, "sector": "writing", "project": "planet",
    "label": "Rédaction de la présentation de Planet"},
  {"uuid": "9421d65b-d42a-fda8-22d7-e37307bd78a0", "date": "019H19",
    "duration": 85, "sector": "programming", "project": "planet",
    "label": "Modification de la représentation des Repositories et restriction de la liste des releases"},
  {"uuid": "bbc5d59e-c02e-068d-ce64-53a033bb08c8", "date": "019H18",
    "duration": 120, "sector": "programming", "project": "planet",
    "label": "Enrichissement de Org avec des block de code paramétrables"},
  {"uuid": "9b6d6398-8cfc-804d-e159-637816dd5cab", "date": "019H18",
    "duration": 320, "sector": "writing", "project": "planet",
    "label": "Expérimentations et description des premières extensions de ROE"},
  {"uuid": "b7fb6cf8-2f4f-9e99-a2ef-037156f3b28e", "date": "019H18",
    "duration": 100, "sector": "visual", "project": "planet",
    "label": "Recherches pour les citations de ROE"},
  {"uuid": "35748446-40df-b1d1-5153-779d62f40fa9", "date": "019H18",
    "duration": 60, "sector": "visual", "project": "planet",
    "label": "Mise en forme des citations dans ROE"},
  {"uuid": "be724d4f-4c29-8db9-20d2-ee7e9a32ee6d", "date": "019H18",
    "duration": 30, "sector": "visual", "project": "planet",
    "label": "Images du lore potentiel"},
  {"uuid": "6b3e5f15-db6c-941f-b4b2-44c961a51065", "date": "019H17",
    "duration": 120, "sector": "programming", "project": "planet",
    "label": "Initiation du block de suivi dans les pages de projets"},
  {"uuid": "3c03a5d0-0a98-683a-7b8f-560ba14ba4c8", "date": "019H17",
    "duration": 120, "sector": "visual", "project": "planet",
    "label": "Initiation du block de suivi dans la page projet, partie visuelle"},
  {"uuid": "fe4b001e-8a73-eb44-a913-e757d55ff505", "date": "019H17",
    "duration": 320, "sector": "visual", "project": "planet",
    "label": "Design des graphiques de secteurs pour les projets"},
  {"uuid": "10238315-3994-b9a5-2db4-b9722c5e55b5", "date": "019H17",
    "duration": 120, "sector": "research", "project": "planet",
    "label": "Recherches et expérimentations pour enrichir le markup de Planet"},
  {"uuid": "38ed746a-7151-21d0-7027-b25377c67360", "date": "019H16",
    "duration": 60, "sector": "visual", "project": "planet",
    "label": "Ajout d'un block de suivi du timetracking par projets"},
  {"uuid": "2f1ee4f0-5eb2-89a8-be79-dbe4aead5ed9", "date": "019H16",
    "duration": 120, "sector": "programming", "project": "planet",
    "label": "Tâches variées et correctif des accents dans les logs"},
  {"uuid": "7cf05675-9841-4238-8633-d8b8d4740fd9", "date": "019H15",
    "duration": 20, "sector": "programming", "project": "planet",
    "label": "Amélioration de la traversée des logs"},
  {"uuid": "2c19127c-fa4f-4ddd-7415-507545ecd6c5", "date": "019H15",
    "duration": 60, "sector": "programming", "project": "planet",
    "label": "Réécriture des contextes de génération"},
  {"uuid": "06d5e4c5-7cfc-5024-9231-ba3dd8c20606", "date": "019H15",
    "duration": 120, "sector": "programming", "project": "planet",
    "label": "Remonter les données des logs dans les pages de projets"},
  {"uuid": "d5b7f2b0-561f-853d-88dd-a6057b603909", "date": "019H15",
    "duration": 25, "sector": "visual", "project": "planet",
    "label": "Modification de l'UI des projets"},
  {"uuid": "aa259e69-7912-a7cb-ffb1-e6d0c9e07217", "date": "019H15",
    "duration": 60, "sector": "visual", "project": "planet",
    "label": "Modification de l'UI des projets"},
  {"uuid": "d04d46ba-e89c-66fc-0db1-2c062ca0638b", "date": "019H14",
    "duration": 60, "sector": "research", "project": null,
    "label": "Histoire du web, Alexandria"},
  {"uuid": "6787ddbc-d30e-5515-06aa-fa0ba6b19e28", "date": "019H13",
    "duration": 120, "sector": "programming", "project": "planet",
    "label": "Ajout de différentes fonctionnalités"},
  {"uuid": "2b616bde-a229-6646-1a89-b0d908214b16", "date": "019H13",
    "duration": 120, "sector": "programming", "project": "planet",
    "label": "Tâches diverses"},
  {"uuid": "ed80c8e0-1db7-1997-6703-92f4ee70b73e", "date": "019H10",
    "duration": 30, "sector": "programming", "project": "planet",
    "label": "Affichage des releases dans la page des projets"},
  {"uuid": "c35e096f-3ad0-ac77-4644-6449364da119", "date": "019H10",
    "duration": 20, "sector": "programming", "project": "planet",
    "label": "Experience using clear screen"},
  {"uuid": "d68fc31f-f357-2323-d781-cf715cfa6b30", "date": "019H10",
    "duration": 10, "sector": "programming", "project": "planet",
    "label": "Fix du clean de l'écran"},
  {"uuid": "e2b6754a-c388-b424-8be9-89629e174431", "date": "019H10",
    "duration": 15, "sector": "visual", "project": "planet",
    "label": "UI Tweak sur les projets"},
  {"uuid": "773e95ac-1388-a5ea-ab12-f64b992bbd01", "date": "019H09",
    "duration": 320, "sector": "programming", "project": "planet",
    "label": "Initialisation de l'UI des projets"},
  {"uuid": "7439ce4d-6699-2a02-a8f9-2302f4cbdad6", "date": "019H08",
    "duration": 60, "sector": "programming", "project": "planet",
    "label": "Mise en place du client (OCaml et JavaScript)"},
  {"uuid": "84da3b00-b4cc-6fb8-23aa-7c4b08eb9c91", "date": "019H08",
    "duration": 120, "sector": "programming", "project": "planet",
    "label": "Initiation du client"},
  {"uuid": "b71009f5-dc71-90ae-f006-383da436a0d7", "date": "019H07",
    "duration": 60, "sector": "visual", "project": "planet",
    "label": "UI de la page projets"},
  {"uuid": "b588d51e-9d86-f6a2-c728-26a85fc59362", "date": "019H06",
    "duration": 120, "sector": "programming", "project": "planet",
    "label": "Injection des metadonnées dans la page de projet"},
  {"uuid": "727e0166-a1b2-c58c-37d7-7afb43918f7f", "date": "019H06",
    "duration": 60, "sector": "programming", "project": "planet",
    "label": "Démarrage de la présentation de projets"},
  {"uuid": "8cf51343-8c5a-6573-0fe8-484abd47a36f", "date": "019H06",
    "duration": 20, "sector": "programming", "project": "planet",
    "label": "Correctif des tables de mises à jours des projets"},
  {"uuid": "5ab036d1-d758-19e1-df52-488279dab34e", "date": "019H05",
    "duration": 30, "sector": "writing", "project": "phragment",
    "label": "Refonte de l'introduction"},
  {"uuid": "96c57fab-e6fb-7a85-bf0d-6fea5843f164", "date": "019H05",
    "duration": 15, "sector": "programming", "project": "planet",
    "label": "Amélioration des routines de build"},
  {"uuid": "dbf9e5f1-3fa9-a58f-cd8c-ab1d9cbecf62", "date": "019H03",
    "duration": 120, "sector": "writing", "project": "phragment",
    "label": "Introduction et contextualisation"},
  {"uuid": "585d325d-cbb0-358a-b033-09bd913a69eb", "date": "019H02",
    "duration": 30, "sector": "visual", "project": "phragment",
    "label": "Iconographie"},
  {"uuid": "95c55fde-060c-150e-5df9-f866eb74ca85", "date": "019G30",
    "duration": 120, "sector": "research", "project": "phragment",
    "label": "Raisonnement sur le manifeste"},
  {"uuid": "07e7985f-762d-a26d-c185-2ec73f048136", "date": "019G29",
    "duration": 200, "sector": "research", "project": "phragment",
    "label": "Raisonnement sur le protocol"},
  {"uuid": "af7f8aa2-4720-756f-8d41-8b2e612623b8", "date": "019G28",
    "duration": 10, "sector": "programming", "project": "planet",
    "label": "Ajout d'un champ typographie pour les projets"},
  {"uuid": "b6faaabf-c1ae-801e-0f63-e42a1c04af8c", "date": "019G28",
    "duration": 200, "sector": "research", "project": "phragment",
    "label": "Initiation du projet"},
  {"uuid": "c3485df3-5ed3-b950-f3aa-1cd8bc805130", "date": "019G27",
    "duration": 60, "sector": "programming", "project": "planet",
    "label": "Tracking des mises à jours pour chaques projets"},
  {"uuid": "bdcbfb41-cc74-6712-c013-23b7ff50aea7", "date": "019G27",
    "duration": 15, "sector": "programming", "project": "planet",
    "label": "Commit des tables d'updates"},
  {"uuid": "18c42d65-7aa2-32de-f925-9567fb38d094", "date": "019G27",
    "duration": 30, "sector": "programming", "project": "planet",
    "label": "Tri des projets par dernière mise à jour"},
  {"uuid": "04373152-9702-b3a6-16ae-ed5b0c9f9bf8", "date": "019G27",
    "duration": 10, "sector": "research", "project": "rutsch",
    "label": "Expérimentations avec le toplevel d'OCaml"},
  {"uuid": "d192acac-0b8e-de9b-5bdd-80cb0b912851", "date": "019G27",
    "duration": 60, "sector": "visual", "project": "planet",
    "label": "Mise en forme de la liste des projets"},
  {"uuid": "fecd16fd-dc8a-f322-d64a-2b9471f53cc5", "date": "019G26",
    "duration": 5, "sector": "programming", "project": "planet",
    "label": "Suppression de secteurs inutiles"},
  {"uuid": "012682a6-722e-4c29-f86a-0a736eb3b3e1", "date": "019G26",
    "duration": 1, "sector": "research", "project": null,
    "label": "Expérience sur les accents & caractères spéciaux"},
  {"uuid": "51c679c8-9ba5-c7ac-40d2-d267eca575ee", "date": "019G26",
    "duration": 5, "sector": "programming", "project": "planet",
    "label": "Amélioration de l'API des tables de raffraichissement"},
  {"uuid": "ed3bcf4f-fe38-79ab-f6bc-fb6c4e039827", "date": "019G24",
    "duration": 30, "sector": "programming", "project": "planet",
    "label": "Introduction des `updated_at` pour les projets"},
  {"uuid": "c8be5a9e-ea85-c0e8-518f-d75a6b7fc07b", "date": "019G22",
    "duration": 320, "sector": "programming", "project": "planet",
    "label": "Génération des projets de Planet à Hakyll (et autres tâches de design)"},
  {"uuid": "a53804c4-2822-aa05-77ce-601883d38ddf", "date": "019G22",
    "duration": 15, "sector": "programming", "project": "planet",
    "label": "Organisation des projets par activité"},
  {"uuid": "1abfdc05-c011-47c5-7736-fb38f6a99f1b", "date": "019G22",
    "duration": 120, "sector": "programming", "project": "planet",
    "label": "Rendus des projets en Q-expression"},
  {"uuid": "fbb10b5f-8efd-a43d-c680-33e74bb2ff4c", "date": "019G21",
    "duration": 60, "sector": "programming", "project": "planet",
    "label": "Design de l'application web"},
  {"uuid": "54560ac8-818b-f1d4-5fc1-dcdb7e3a8ac2", "date": "019G21",
    "duration": 120, "sector": "programming", "project": "planet",
    "label": "Design de l'interface de Planet"},
  {"uuid": "723aea1a-38d5-f936-aefb-c5fc99e72db8", "date": "019G21",
    "duration": 120, "sector": "visual", "project": "planet",
    "label": "Plusieurs expériences de layout"},
  {"uuid": "f6feb336-4037-92a3-7d1a-fe7f4e90168c", "date": "019G10",
    "duration": 120, "sector": "programming", "project": "planet",
    "label": "Utilisation dans la syntaxe monadique pour une majeure partie du module PaperWork"},
  {"uuid": "a5391f23-3b7f-fd86-3bbe-c225151f1bd5", "date": "019F29",
    "duration": 20, "sector": "programming", "project": "planet",
    "label": "Expérience sur le let-operator en OCaml"},
  {"uuid": "23593b06-ad13-32b7-4a71-b5cfaaef3ccf", "date": "019F26",
    "duration": 600, "sector": "writing", "project": null,
    "label": "Réécriture complète du talk sur les modules pour SunnyTech 2019"},
  {"uuid": "a64c3c6f-3857-c731-67aa-e35a4b1e9914", "date": "019F17",
    "duration": 200, "sector": "programming", "project": "quasar",
    "label": "Ajout de tests"},
  {"uuid": "a57e28e1-c39a-bdfd-8540-e4013291aa49", "date": "019F17",
    "duration": 120, "sector": "programming", "project": "planet",
    "label": "Combats avec Stack/Cabal pour initier Hakyll"},
  {"uuid": "84643f55-f16e-b9db-0fcf-4162a35d77c0", "date": "019F12",
    "duration": 120, "sector": "programming", "project": "quasar",
    "label": "Amélioration de l'API du binding partiel de Jest"},
  {"uuid": "94a4a526-e214-3d9d-4af0-22640497ac1f", "date": "019F07",
    "duration": 120, "sector": "programming", "project": "quasar",
    "label": "Initiation concrète des tests"},
  {"uuid": "d59457c5-3f59-2641-8e7f-b3bcf9eb4bfa", "date": "019F02",
    "duration": 240, "sector": "programming", "project": "quasar",
    "label": "Progression sur Quasar, initiation des test JavaScript"},
  {"uuid": "9c859300-e4e5-fdc7-f9bc-f262f903c8f6", "date": "019F01",
    "duration": 520, "sector": "programming", "project": "quasar",
    "label": "Implémentation du module Console (pour Node et le navigateur)"},
  {"uuid": "9a7387bc-b051-dd04-c73a-0c84e2a83dbe", "date": "019E31",
    "duration": 400, "sector": "programming", "project": "quasar",
    "label": "Amélioration des premiers composants et réflexion sur les tests"},
  {"uuid": "e6abf390-56ee-be5f-78fd-284b5d7d8184", "date": "019E30",
    "duration": 380, "sector": "programming", "project": "quasar",
    "label": "Implantation du module Js.Array"},
  {"uuid": "440e6604-9f9c-6f0c-9fe2-a2aedb04ce59", "date": "019E30",
    "duration": 60, "sector": "research", "project": null,
    "label": "Fix des dépôts cassés de ma distribution"},
  {"uuid": "16771928-d3f3-38bb-7795-d1602efff014", "date": "019E29",
    "duration": 240, "sector": "programming", "project": "quasar",
    "label": "Démarrage de l'organisation des fichiers et implémentation d'un premier module"},
  {"uuid": "b8d6ef73-e836-bcb9-2575-9bf935fb1bca", "date": "019E28",
    "duration": 240, "sector": "maintenance", "project": null,
    "label": "Maintenance ArchLinux"},
  {"uuid": "bbaff585-cfc1-6ccf-b37d-de976ec752d7", "date": "019E24",
    "duration": 320, "sector": "programming", "project": "quasar",
    "label": "Organisation générale des modules"},
  {"uuid": "df10c94c-f214-870c-c316-c8ef146af53f", "date": "019E20",
    "duration": 120, "sector": "research", "project": "quasar",
    "label": "Réflexion sur l'organisation de Quasar (et expériences d'implémentations)"},
  {"uuid": "c5c106af-8622-6542-f259-512da5b4c846", "date": "019E15",
    "duration": 15, "sector": "programming", "project": "planet",
    "label": "Ajout de projets non publiés"},
  {"uuid": "264876d3-9e86-e3d6-75fa-f5e79d20b105", "date": "019E12",
    "duration": 520, "sector": "writing", "project": null,
    "label": "Ecriture de la présentation pour Paris.Ex 12 (les Macros en Elixir)"},
  {"uuid": "9ea8c26d-f483-c483-56e1-6d4928664585", "date": "019E10",
    "duration": 60, "sector": "programming", "project": "planet",
    "label": "Automatisation des commit des logs"},
  {"uuid": "40352cb2-0301-190a-162c-6db2e95f8a64", "date": "019E10",
    "duration": 120, "sector": "research", "project": "planet",
    "label": "Expériences sur la génération de HTML"},
  {"uuid": "06887915-9e9e-ae1c-f4ce-7a26ddab39e0", "date": "019E06",
    "duration": 320, "sector": "audio", "project": null,
    "label": "Expériences avec Pure Data, Orca, Marabu et Bosca Ceoil pour la fabrication de bruit"},
  {"uuid": "f5ecf238-9e8f-194a-f991-98ea7949e15b", "date": "019E05",
    "duration": 320, "sector": "audio", "project": null,
    "label": "Expériences avec ORCA (construction de bruits)"},
  {"uuid": "6de0a8b0-b50a-62bb-db2b-2ebdb9ceb371", "date": "019E01",
    "duration": 180, "sector": "research", "project": null,
    "label": "Expériences avec Godot Engine "},
  {"uuid": "aed07c03-d62d-1019-02ac-cc8c17acce1c", "date": "019D29",
    "duration": 120, "sector": "research", "project": null,
    "label": "Lecture sur l'implémentation d'un système de type et sur l'inférence"},
  {"uuid": "2607039d-5595-0c4a-94bc-70bbbbcd1205", "date": "019D29",
    "duration": 200, "sector": "programming", "project": "brainfocaml",
    "label": "Amélioration du Parseur et initiation des premiers tests"},
  {"uuid": "d511b109-254d-5ec6-efb5-45ebd1934639", "date": "019D29",
    "duration": 300, "sector": "research", "project": "planet",
    "label": "Expérimentations sur la génération de pages"},
  {"uuid": "092cdf82-20ae-203a-9c47-d4357b0b7488", "date": "019D26",
    "duration": 60, "sector": "programming", "project": "brainfocaml",
    "label": "Réécriture du Parseur"},
  {"uuid": "76a8cfb5-a649-0137-856d-c0e92242062e", "date": "019D26",
    "duration": 120, "sector": "programming", "project": "brainfocaml",
    "label": "Réflexion sur les fonctionnalités (inutiles :P) attendues et implémentation du Parseur"},
  {"uuid": "cd28d55d-fefa-be36-fdc9-400ce2289442", "date": "019D25",
    "duration": 60, "sector": "programming", "project": "brainfocaml",
    "label": "Reconstruction du projet avec un tooling OCaml moderne (Dune, ocamlformat etc.)"},
  {"uuid": "e2c87eb5-cfaa-319c-f6e3-eb9bc179667d", "date": "019D23",
    "duration": 120, "sector": "research", "project": null,
    "label": "Expérimentation sur Nix et NixOS"},
  {"uuid": "65f9391c-887b-0d8e-1e73-b9381334d8af", "date": "019D18",
    "duration": 320, "sector": "research", "project": null,
    "label": "Recherches sur les modules ML"},
  {"uuid": "65f9391c-887b-0d8e-1e73-b9381334d8af", "date": "019D17",
    "duration": 240, "sector": "research", "project": null,
    "label": "Recherches sur les modules ML"},
  {"uuid": "65f9391c-887b-0d8e-1e73-b9381334d8af", "date": "019D16",
    "duration": 180, "sector": "research", "project": null,
    "label": "Recherches sur les modules ML"},
  {"uuid": "65f9391c-887b-0d8e-1e73-b9381334d8af", "date": "019D15",
    "duration": 200, "sector": "research", "project": null,
    "label": "Recherches sur les modules ML"},
  {"uuid": "97af129d-dc65-c78c-98bc-d98c37641f95", "date": "019D14",
    "duration": 30, "sector": "programming", "project": "planet",
    "label": "Ajout d'une interface pour exécuter des commandes Shell"},
  {"uuid": "f6fe00d3-b8fd-bf90-fc0e-422c3ae344af", "date": "019D13",
    "duration": 420, "sector": "research", "project": null,
    "label": "Les modules dans différents langages de programmation, talk DevoxxFR 2019"},
  {"uuid": "559fa1bf-a74c-5ee2-57bd-2050fa3ad845", "date": "019D12",
    "duration": 120, "sector": "research", "project": null,
    "label": "Le langage de modules de OCaml pour le talk à DevoxxFR 2019"},
  {"uuid": "9ff7f66c-57cc-380a-3f17-aaf41552be3e", "date": "019D10",
    "duration": 60, "sector": "writing", "project": null,
    "label": "Expérience sur la génération de récits"},
  {"uuid": "88799ad5-0873-07f4-9887-bc5a67364123", "date": "019D09",
    "duration": 120, "sector": "research", "project": null,
    "label": "Progression dans 'Logique du récit' de Claude Brémond"},
  {"uuid": "9d88986a-9557-c74b-8956-41af56d9e7d4", "date": "019D08",
    "duration": 120, "sector": "programming", "project": "planet",
    "label": "Génération des logs en Json"},
  {"uuid": "39b8517f-7ada-4177-6413-2e40430fe6fc", "date": "019D07",
    "duration": 120, "sector": "programming", "project": "planet",
    "label": "Implémentation d'un module pour générer du Json"},
  {"uuid": "7686c709-a704-2690-f598-e906f619d3aa", "date": "019D07",
    "duration": 240, "sector": "programming", "project": "planet",
    "label": "Implémentation de divers générateurs"},
  {"uuid": "309d8207-86e1-01db-5171-60c51d696714", "date": "019D06",
    "duration": 240, "sector": "research", "project": null,
    "label": "Progression dans 'Logique du récit' de Claude Brémond"},
  {"uuid": "217b04d4-43f4-9517-a429-9f011c822001", "date": "019D05",
    "duration": 180, "sector": "research", "project": null,
    "label": "Lecture de 'Logique du récit' de Claude Brémond"},
  {"uuid": "afa794ba-89c8-e242-b385-cf99c694dd83", "date": "019D04",
    "duration": 180, "sector": "research", "project": null,
    "label": "Formation 'Domain Driven Design' avec FSharp"},
  {"uuid": "3d26c72c-74b8-5990-1e94-62b2594714f4", "date": "019D03",
    "duration": 100, "sector": "research", "project": null,
    "label": "Lecture sur la sémantique structurale de Greimas"},
  {"uuid": "1addc3be-aca5-ff61-9511-4197b90a8985", "date": "019D03",
    "duration": 120, "sector": "programming", "project": "qian",
    "label": "Nettoyage du projet et mise à jours des dépendances (et développement bref)"},
  {"uuid": "e8c3248e-69e5-1e12-c52f-3fd9d6c133d6", "date": "019D03",
    "duration": 180, "sector": "programming", "project": "qian",
    "label": "Nettoyage du projet en vue de la V2. Bataille avec Webpack !"},
  {"uuid": "4df3ccba-f903-e06a-c3d0-c5dded423dab", "date": "019D02",
    "duration": 180, "sector": "research", "project": null,
    "label": "Relecture de documents sur le Domain Driven Design"},
  {"uuid": "9236ebe2-5039-14f2-dea3-1669a97e45aa", "date": "019D01",
    "duration": 60, "sector": "programming", "project": "planet",
    "label": "Enregistrement de la ville où je me trouve"},
  {"uuid": "3817ed2a-3480-3477-e072-1f730191ca20", "date": "019D01",
    "duration": 30, "sector": "programming", "project": "planet",
    "label": "Préparation de la routine de 'build' de l'application web"},
  {"uuid": "3d3b2037-0e46-e3eb-fa0a-2ebfab6facb5", "date": "019C28",
    "duration": 120, "sector": "research", "project": null,
    "label": "Documentation et expériences avec MirageOS"},
  {"uuid": "df34f3bc-881c-21f3-09b6-db56890b54bc", "date": "019C27",
    "duration": 10, "sector": "programming", "project": "planet",
    "label": "Correction de l'ajout de tâches"},
  {"uuid": "4ad085c6-a24c-ae21-d124-2fe7cc1834b3", "date": "019C27",
    "duration": 120, "sector": "programming", "project": "planet",
    "label": "Initiation des programmes 'ego' et 'remor'"},
  {"uuid": "5f41f62a-9b24-c7fa-8e85-c01d90d974a2", "date": "019C06",
    "duration": 15, "sector": "writing", "project": "planet",
    "label": "Initiation de la description de Qian"},
  {"uuid": "4e05df5b-b919-86f7-488c-f06393cf3f24", "date": "019C06",
    "duration": 15, "sector": "programming", "project": "planet",
    "label": "Suppression d'un retour à la ligne dans les dumps"},
  {"uuid": "6ba26d8a-00fe-6bbe-3b86-c75ccbc2f8ba", "date": "019C03",
    "duration": 60, "sector": "programming", "project": "planet",
    "label": "Ajout d'une CLI pour la saisie des logs"},
  {"uuid": "c20e01c5-19c5-5686-7d70-18bbd196a5c2", "date": "019C01",
    "duration": 280, "sector": "programming", "project": "planet",
    "label": "Ajout d'un système de saisie de log interactif via `./log.exe i[nteractive]`"},
  {"uuid": "64d3510c-7e54-2f11-4793-86a646ef049f", "date": "019C01",
    "duration": 15, "sector": "programming", "project": "planet",
    "label": "Amélioration de la saisie interactive (suppression des confirmations inutiles)"},
  {"uuid": "77169692-1932-1c19-228a-e3f3f7db999d", "date": "019A06",
    "duration": 120, "sector": "programming", "project": "planet",
    "label": "Initiation du projet"},
  {"uuid": "fa7a5ea2-8c75-7a1b-d3af-10780067f66f", "date": "018A23",
    "duration": 60, "sector": "maintenance", "project": "qian",
    "label": "Correctif de failles de sécurités et release 1.3.2"},
  {"uuid": "27121442-fc0f-8ac2-e83e-780c63524823", "date": "017K05",
    "duration": 480, "sector": "programming", "project": "qian",
    "label": "Initiation du projet"},
  {"uuid": "76c8fa60-3b1c-07ea-21c1-bafd15a93aff", "date": "015H24",
    "duration": 700, "sector": "writing", "project": "almost_heroic",
    "label": "Ecriture des dialogues"},
  {"uuid": "5eadb8d5-6381-1831-f38c-abd6710c61c0", "date": "015H23",
    "duration": 600, "sector": "programming", "project": "almost_heroic",
    "label": "Programmation des différents systèmes"},
  {"uuid": "907faa66-aa39-da07-a555-6a7509668c3e", "date": "015H22",
    "duration": 580, "sector": "visual", "project": "almost_heroic",
    "label": "Level design des différents niveaux"}]